{
 "Atlanta Utd": {
  "time": "Atlanta Utd",
  "n_jogos_total": 5,
  "n_casa": 3,
  "n_fora": 2,
  "volume": {
   "casa_pro_ft": 4.67,
   "casa_sof_ft": 4.67,
   "casa_total_ft": 9.33,
   "fora_pro_ft": 8.5,
   "fora_sof_ft": 6,
   "fora_total_ft": 14.5
  },
  "pos_gol_pro": null,
  "pos_gol_contra": null,
  "distribuicao_HT2T": {
   "pct_ht": 61.3,
   "categoria": "BLITZ_INICIAL",
   "ht_pro_avg": 3.8,
   "t2_pro_avg": 2.4
  },
  "sangrador": {
   "sof_avg": 5.2,
   "posse_avg": 53,
   "tipo": "NORMAL"
  },
  "eficacia": {
   "cantos_por_gol": 4.43,
   "categoria": "NORMAL",
   "total_gols": 7,
   "total_cantos": 31
  },
  "regime_atual": {
   "status": "⚪ NEUTRO",
   "obs": "Sem direção clara | sd 2.9 | desvio +0.3",
   "ultimos_jogos": [
    7,
    3,
    6,
    10
   ]
  },
  "historico": [
   {
    "data": "18.04.2026 20:30",
    "rodada": "R7",
    "local": "CASA",
    "adv": "Nashville SC",
    "c_pro_ht": 1,
    "c_sof_ht": 4,
    "c_pro_2t": 4,
    "c_sof_2t": 3,
    "c_pro_ft": 5,
    "c_sof_ft": 7,
    "gols_pro_ht": 0,
    "gols_sof_ht": 0,
    "gols_pro_ft": 0,
    "gols_sof_ft": 2,
    "posse": 55,
    "fin": 13
   },
   {
    "data": "25.04.2026 14:00",
    "rodada": "R8",
    "local": "FORA",
    "adv": "Toronto FC",
    "c_pro_ht": 5,
    "c_sof_ht": 1,
    "c_pro_2t": 2,
    "c_sof_2t": 7,
    "c_pro_ft": 7,
    "c_sof_ft": 8,
    "gols_pro_ht": 0,
    "gols_sof_ht": 0,
    "gols_pro_ft": 2,
    "gols_sof_ft": 1,
    "posse": 49,
    "fin": 6
   },
   {
    "data": "02.05.2026 20:30",
    "rodada": "R9",
    "local": "CASA",
    "adv": "CF Montreal",
    "c_pro_ht": 1,
    "c_sof_ht": 1,
    "c_pro_2t": 2,
    "c_sof_2t": 1,
    "c_pro_ft": 3,
    "c_sof_ft": 2,
    "gols_pro_ht": 2,
    "gols_sof_ht": 1,
    "gols_pro_ft": 3,
    "gols_sof_ft": 1,
    "posse": 53,
    "fin": 18
   },
   {
    "data": "09.05.2026 20:30",
    "rodada": "R10",
    "local": "CASA",
    "adv": "Los Angeles Galaxy",
    "c_pro_ht": 4,
    "c_sof_ht": 1,
    "c_pro_2t": 2,
    "c_sof_2t": 4,
    "c_pro_ft": 6,
    "c_sof_ft": 5,
    "gols_pro_ht": 0,
    "gols_sof_ht": 0,
    "gols_pro_ft": 1,
    "gols_sof_ft": 2,
    "posse": 53,
    "fin": 14
   },
   {
    "data": "16.05.2026 20:30",
    "rodada": "R12",
    "local": "FORA",
    "adv": "Orlando City",
    "c_pro_ht": 8,
    "c_sof_ht": 2,
    "c_pro_2t": 2,
    "c_sof_2t": 2,
    "c_pro_ft": 10,
    "c_sof_ft": 4,
    "gols_pro_ht": 0,
    "gols_sof_ht": 1,
    "gols_pro_ft": 1,
    "gols_sof_ft": 1,
    "posse": 55,
    "fin": 21
   }
  ]
 },
 "Austin FC": {
  "time": "Austin FC",
  "n_jogos_total": 7,
  "n_casa": 3,
  "n_fora": 4,
  "volume": {
   "casa_pro_ft": 3.33,
   "casa_sof_ft": 6,
   "casa_total_ft": 9.33,
   "fora_pro_ft": 3.5,
   "fora_sof_ft": 7,
   "fora_total_ft": 10.5
  },
  "pos_gol_pro": {
   "n": 5,
   "c_2t_pro": 1.2,
   "c_2t_sof": 3.2,
   "diff": -2.0,
   "estilo": "RECUA_POS_GOL"
  },
  "pos_gol_contra": null,
  "distribuicao_HT2T": {
   "pct_ht": 58.3,
   "categoria": "BLITZ_INICIAL",
   "ht_pro_avg": 2,
   "t2_pro_avg": 1.43
  },
  "sangrador": {
   "sof_avg": 6.57,
   "posse_avg": 45.3,
   "tipo": "SANGRA_SEM_BOLA"
  },
  "eficacia": {
   "cantos_por_gol": 2.18,
   "categoria": "CLINICA",
   "total_gols": 11,
   "total_cantos": 24
  },
  "regime_atual": {
   "status": "⚪ NEUTRO",
   "obs": "Sem direção clara | sd 0.5 | desvio +0.3",
   "ultimos_jogos": [
    4,
    4,
    4,
    3
   ]
  },
  "historico": [
   {
    "data": "18.04.2026 14:00",
    "rodada": "R7",
    "local": "FORA",
    "adv": "Toronto FC",
    "c_pro_ht": 4,
    "c_sof_ht": 2,
    "c_pro_2t": 1,
    "c_sof_2t": 4,
    "c_pro_ft": 5,
    "c_sof_ft": 6,
    "gols_pro_ht": 1,
    "gols_sof_ht": 0,
    "gols_pro_ft": 3,
    "gols_sof_ft": 3,
    "posse": 54,
    "fin": 12
   },
   {
    "data": "22.04.2026 23:30",
    "rodada": "R8",
    "local": "FORA",
    "adv": "San Jose Earthquakes",
    "c_pro_ht": 1,
    "c_sof_ht": 6,
    "c_pro_2t": 0,
    "c_sof_2t": 7,
    "c_pro_ft": 1,
    "c_sof_ft": 13,
    "gols_pro_ht": 1,
    "gols_sof_ht": 0,
    "gols_pro_ft": 1,
    "gols_sof_ft": 5,
    "posse": 31,
    "fin": 5
   },
   {
    "data": "25.04.2026 21:30",
    "rodada": "R8",
    "local": "CASA",
    "adv": "Houston Dynamo",
    "c_pro_ht": 1,
    "c_sof_ht": 3,
    "c_pro_2t": 2,
    "c_sof_2t": 2,
    "c_pro_ft": 3,
    "c_sof_ft": 5,
    "gols_pro_ht": 2,
    "gols_sof_ht": 0,
    "gols_pro_ft": 2,
    "gols_sof_ft": 0,
    "posse": 45,
    "fin": 13
   },
   {
    "data": "03.05.2026 18:30",
    "rodada": "R9",
    "local": "CASA",
    "adv": "St. Louis City",
    "c_pro_ht": 2,
    "c_sof_ht": 4,
    "c_pro_2t": 2,
    "c_sof_2t": 2,
    "c_pro_ft": 4,
    "c_sof_ft": 6,
    "gols_pro_ht": 0,
    "gols_sof_ht": 0,
    "gols_pro_ft": 2,
    "gols_sof_ft": 0,
    "posse": 55,
    "fin": 16
   },
   {
    "data": "10.05.2026 20:00",
    "rodada": "R10",
    "local": "FORA",
    "adv": "Minnesota United",
    "c_pro_ht": 3,
    "c_sof_ht": 2,
    "c_pro_2t": 1,
    "c_sof_2t": 1,
    "c_pro_ft": 4,
    "c_sof_ft": 3,
    "gols_pro_ht": 1,
    "gols_sof_ht": 0,
    "gols_pro_ft": 2,
    "gols_sof_ft": 2,
    "posse": 45,
    "fin": 12
   },
   {
    "data": "13.05.2026 22:30",
    "rodada": "R11",
    "local": "FORA",
    "adv": "San Diego FC",
    "c_pro_ht": 2,
    "c_sof_ht": 3,
    "c_pro_2t": 2,
    "c_sof_2t": 3,
    "c_pro_ft": 4,
    "c_sof_ft": 6,
    "gols_pro_ht": 0,
    "gols_sof_ht": 2,
    "gols_pro_ft": 0,
    "gols_sof_ft": 5,
    "posse": 41,
    "fin": 9
   },
   {
    "data": "16.05.2026 21:30",
    "rodada": "R12",
    "local": "CASA",
    "adv": "Sporting Kansas City",
    "c_pro_ht": 1,
    "c_sof_ht": 5,
    "c_pro_2t": 2,
    "c_sof_2t": 2,
    "c_pro_ft": 3,
    "c_sof_ft": 7,
    "gols_pro_ht": 1,
    "gols_sof_ht": 0,
    "gols_pro_ft": 1,
    "gols_sof_ft": 2,
    "posse": 46,
    "fin": 8
   }
  ]
 },
 "CF Montreal": {
  "time": "CF Montreal",
  "n_jogos_total": 6,
  "n_casa": 5,
  "n_fora": 1,
  "volume": {
   "casa_pro_ft": 7.6,
   "casa_sof_ft": 4.6,
   "casa_total_ft": 12.2,
   "fora_pro_ft": 2,
   "fora_sof_ft": 3,
   "fora_total_ft": 5
  },
  "pos_gol_pro": {
   "n": 3,
   "c_2t_pro": 3.33,
   "c_2t_sof": 3,
   "diff": 0.33,
   "estilo": "EQUILIBRADO_POS_GOL"
  },
  "pos_gol_contra": {
   "n": 2,
   "c_2t_pro": 6.5,
   "c_2t_sof": 2,
   "diff": 4.5,
   "estilo": "REAGE_PRESSIONA"
  },
  "distribuicao_HT2T": {
   "pct_ht": 25.0,
   "categoria": "ASFIXIA_FINAL",
   "ht_pro_avg": 1.67,
   "t2_pro_avg": 5
  },
  "sangrador": {
   "sof_avg": 4.33,
   "posse_avg": 44.8,
   "tipo": "NORMAL"
  },
  "eficacia": {
   "cantos_por_gol": 4.0,
   "categoria": "NORMAL",
   "total_gols": 10,
   "total_cantos": 40
  },
  "regime_atual": {
   "status": "🔴 QUEBRADO",
   "obs": "Alta variância nos últimos jogos (sd 6.1) | sem padrão claro",
   "ultimos_jogos": [
    2,
    11,
    6,
    16
   ]
  },
  "historico": [
   {
    "data": "18.04.2026 15:30",
    "rodada": "R7",
    "local": "CASA",
    "adv": "New York Red Bulls",
    "c_pro_ht": 0,
    "c_sof_ht": 3,
    "c_pro_2t": 2,
    "c_sof_2t": 4,
    "c_pro_ft": 2,
    "c_sof_ft": 7,
    "gols_pro_ht": 2,
    "gols_sof_ht": 0,
    "gols_pro_ft": 4,
    "gols_sof_ft": 1,
    "posse": 32,
    "fin": 9
   },
   {
    "data": "25.04.2026 15:30",
    "rodada": "R8",
    "local": "CASA",
    "adv": "New York City",
    "c_pro_ht": 0,
    "c_sof_ht": 0,
    "c_pro_2t": 3,
    "c_sof_2t": 1,
    "c_pro_ft": 3,
    "c_sof_ft": 1,
    "gols_pro_ht": 1,
    "gols_sof_ht": 0,
    "gols_pro_ft": 1,
    "gols_sof_ft": 0,
    "posse": 35,
    "fin": 8
   },
   {
    "data": "02.05.2026 20:30",
    "rodada": "R9",
    "local": "FORA",
    "adv": "Atlanta Utd",
    "c_pro_ht": 1,
    "c_sof_ht": 1,
    "c_pro_2t": 1,
    "c_sof_2t": 2,
    "c_pro_ft": 2,
    "c_sof_ft": 3,
    "gols_pro_ht": 1,
    "gols_sof_ht": 2,
    "gols_pro_ft": 1,
    "gols_sof_ft": 3,
    "posse": 47,
    "fin": 11
   },
   {
    "data": "09.05.2026 17:30",
    "rodada": "R10",
    "local": "CASA",
    "adv": "Orlando City",
    "c_pro_ht": 4,
    "c_sof_ht": 1,
    "c_pro_2t": 7,
    "c_sof_2t": 2,
    "c_pro_ft": 11,
    "c_sof_ft": 3,
    "gols_pro_ht": 0,
    "gols_sof_ht": 0,
    "gols_pro_ft": 2,
    "gols_sof_ft": 0,
    "posse": 53,
    "fin": 23
   },
   {
    "data": "13.05.2026 20:30",
    "rodada": "R11",
    "local": "CASA",
    "adv": "Portland Timbers",
    "c_pro_ht": 1,
    "c_sof_ht": 5,
    "c_pro_2t": 5,
    "c_sof_2t": 4,
    "c_pro_ft": 6,
    "c_sof_ft": 9,
    "gols_pro_ht": 2,
    "gols_sof_ht": 1,
    "gols_pro_ft": 2,
    "gols_sof_ft": 2,
    "posse": 43,
    "fin": 23
   },
   {
    "data": "16.05.2026 17:30",
    "rodada": "R12",
    "local": "CASA",
    "adv": "Chicago Fire",
    "c_pro_ht": 4,
    "c_sof_ht": 1,
    "c_pro_2t": 12,
    "c_sof_2t": 2,
    "c_pro_ft": 16,
    "c_sof_ft": 3,
    "gols_pro_ht": 0,
    "gols_sof_ht": 1,
    "gols_pro_ft": 0,
    "gols_sof_ft": 2,
    "posse": 59,
    "fin": 15
   }
  ]
 },
 "Charlotte": {
  "time": "Charlotte",
  "n_jogos_total": 6,
  "n_casa": 3,
  "n_fora": 3,
  "volume": {
   "casa_pro_ft": 7.33,
   "casa_sof_ft": 3,
   "casa_total_ft": 10.33,
   "fora_pro_ft": 3.33,
   "fora_sof_ft": 5,
   "fora_total_ft": 8.33
  },
  "pos_gol_pro": null,
  "pos_gol_contra": {
   "n": 3,
   "c_2t_pro": 3.67,
   "c_2t_sof": 2,
   "diff": 1.67,
   "estilo": "REAGE_PRESSIONA"
  },
  "distribuicao_HT2T": {
   "pct_ht": 43.8,
   "categoria": "DISTRIBUIDO",
   "ht_pro_avg": 2.33,
   "t2_pro_avg": 3
  },
  "sangrador": {
   "sof_avg": 4,
   "posse_avg": 43.3,
   "tipo": "NORMAL"
  },
  "eficacia": {
   "cantos_por_gol": 3.56,
   "categoria": "NORMAL",
   "total_gols": 9,
   "total_cantos": 32
  },
  "regime_atual": {
   "status": "🟡 EMERGENTE",
   "obs": "Tendência emergente em alta | sd 1.3 | desvio +1.4",
   "ultimos_jogos": [
    5,
    7,
    8,
    7
   ]
  },
  "historico": [
   {
    "data": "18.04.2026 20:30",
    "rodada": "R7",
    "local": "FORA",
    "adv": "New York City",
    "c_pro_ht": 0,
    "c_sof_ht": 3,
    "c_pro_2t": 1,
    "c_sof_2t": 3,
    "c_pro_ft": 1,
    "c_sof_ft": 6,
    "gols_pro_ht": 0,
    "gols_sof_ht": 0,
    "gols_pro_ft": 2,
    "gols_sof_ft": 1,
    "posse": 36,
    "fin": 7
   },
   {
    "data": "25.04.2026 21:30",
    "rodada": "R8",
    "local": "FORA",
    "adv": "Nashville SC",
    "c_pro_ht": 0,
    "c_sof_ht": 4,
    "c_pro_2t": 4,
    "c_sof_2t": 2,
    "c_pro_ft": 4,
    "c_sof_ft": 6,
    "gols_pro_ht": 1,
    "gols_sof_ht": 2,
    "gols_pro_ft": 2,
    "gols_sof_ft": 4,
    "posse": 39,
    "fin": 8
   },
   {
    "data": "02.05.2026 20:30",
    "rodada": "R9",
    "local": "FORA",
    "adv": "New England Revolution",
    "c_pro_ht": 3,
    "c_sof_ht": 2,
    "c_pro_2t": 2,
    "c_sof_2t": 1,
    "c_pro_ft": 5,
    "c_sof_ft": 3,
    "gols_pro_ht": 0,
    "gols_sof_ht": 0,
    "gols_pro_ft": 0,
    "gols_sof_ft": 1,
    "posse": 45,
    "fin": 9
   },
   {
    "data": "09.05.2026 20:30",
    "rodada": "R10",
    "local": "CASA",
    "adv": "FC Cincinnati",
    "c_pro_ht": 3,
    "c_sof_ht": 2,
    "c_pro_2t": 4,
    "c_sof_2t": 2,
    "c_pro_ft": 7,
    "c_sof_ft": 4,
    "gols_pro_ht": 0,
    "gols_sof_ht": 2,
    "gols_pro_ft": 2,
    "gols_sof_ft": 2,
    "posse": 47,
    "fin": 12
   },
   {
    "data": "13.05.2026 20:15",
    "rodada": "R11",
    "local": "CASA",
    "adv": "New York City",
    "c_pro_ht": 5,
    "c_sof_ht": 0,
    "c_pro_2t": 3,
    "c_sof_2t": 2,
    "c_pro_ft": 8,
    "c_sof_ft": 2,
    "gols_pro_ht": 0,
    "gols_sof_ht": 1,
    "gols_pro_ft": 0,
    "gols_sof_ft": 1,
    "posse": 47,
    "fin": 5
   },
   {
    "data": "16.05.2026 20:30",
    "rodada": "R12",
    "local": "CASA",
    "adv": "Toronto FC",
    "c_pro_ht": 3,
    "c_sof_ht": 1,
    "c_pro_2t": 4,
    "c_sof_2t": 2,
    "c_pro_ft": 7,
    "c_sof_ft": 3,
    "gols_pro_ht": 2,
    "gols_sof_ht": 1,
    "gols_pro_ft": 3,
    "gols_sof_ft": 1,
    "posse": 46,
    "fin": 18
   }
  ]
 },
 "Chicago Fire": {
  "time": "Chicago Fire",
  "n_jogos_total": 6,
  "n_casa": 3,
  "n_fora": 3,
  "volume": {
   "casa_pro_ft": 6.67,
   "casa_sof_ft": 2,
   "casa_total_ft": 8.67,
   "fora_pro_ft": 4,
   "fora_sof_ft": 10.67,
   "fora_total_ft": 14.67
  },
  "pos_gol_pro": {
   "n": 2,
   "c_2t_pro": 1,
   "c_2t_sof": 8,
   "diff": -7,
   "estilo": "RECUA_POS_GOL"
  },
  "pos_gol_contra": {
   "n": 2,
   "c_2t_pro": 4.5,
   "c_2t_sof": 3.5,
   "diff": 1.0,
   "estilo": "REAGE_PRESSIONA"
  },
  "distribuicao_HT2T": {
   "pct_ht": 34.4,
   "categoria": "ASFIXIA_FINAL",
   "ht_pro_avg": 1.83,
   "t2_pro_avg": 3.5
  },
  "sangrador": {
   "sof_avg": 6.33,
   "posse_avg": 56.2,
   "tipo": "SANGRA_COM_BOLA"
  },
  "eficacia": {
   "cantos_por_gol": 2.0,
   "categoria": "CLINICA",
   "total_gols": 16,
   "total_cantos": 32
  },
  "regime_atual": {
   "status": "⚪ NEUTRO",
   "obs": "Sem direção clara | sd 3.0 | desvio +1.4",
   "ultimos_jogos": [
    10,
    6,
    8,
    3
   ]
  },
  "historico": [
   {
    "data": "18.04.2026 20:30",
    "rodada": "R7",
    "local": "FORA",
    "adv": "FC Cincinnati",
    "c_pro_ht": 1,
    "c_sof_ht": 5,
    "c_pro_2t": 0,
    "c_sof_2t": 4,
    "c_pro_ft": 1,
    "c_sof_ft": 9,
    "gols_pro_ht": 2,
    "gols_sof_ht": 1,
    "gols_pro_ft": 3,
    "gols_sof_ft": 3,
    "posse": 45,
    "fin": 18
   },
   {
    "data": "25.04.2026 21:30",
    "rodada": "R8",
    "local": "CASA",
    "adv": "Sporting Kansas City",
    "c_pro_ht": 1,
    "c_sof_ht": 0,
    "c_pro_2t": 3,
    "c_sof_2t": 2,
    "c_pro_ft": 4,
    "c_sof_ft": 2,
    "gols_pro_ht": 0,
    "gols_sof_ht": 0,
    "gols_pro_ft": 5,
    "gols_sof_ft": 0,
    "posse": 71,
    "fin": 17
   },
   {
    "data": "02.05.2026 21:30",
    "rodada": "R9",
    "local": "CASA",
    "adv": "FC Cincinnati",
    "c_pro_ht": 3,
    "c_sof_ht": 0,
    "c_pro_2t": 7,
    "c_sof_2t": 1,
    "c_pro_ft": 10,
    "c_sof_ft": 1,
    "gols_pro_ht": 2,
    "gols_sof_ht": 2,
    "gols_pro_ft": 2,
    "gols_sof_ft": 3,
    "posse": 56,
    "fin": 33
   },
   {
    "data": "09.05.2026 15:30",
    "rodada": "R10",
    "local": "CASA",
    "adv": "New York Red Bulls",
    "c_pro_ht": 2,
    "c_sof_ht": 0,
    "c_pro_2t": 4,
    "c_sof_2t": 3,
    "c_pro_ft": 6,
    "c_sof_ft": 3,
    "gols_pro_ht": 0,
    "gols_sof_ht": 1,
    "gols_pro_ft": 1,
    "gols_sof_ft": 3,
    "posse": 64,
    "fin": 15
   },
   {
    "data": "13.05.2026 20:30",
    "rodada": "R11",
    "local": "FORA",
    "adv": "DC United",
    "c_pro_ht": 3,
    "c_sof_ht": 3,
    "c_pro_2t": 5,
    "c_sof_2t": 4,
    "c_pro_ft": 8,
    "c_sof_ft": 7,
    "gols_pro_ht": 0,
    "gols_sof_ht": 1,
    "gols_pro_ft": 3,
    "gols_sof_ft": 1,
    "posse": 60,
    "fin": 14
   },
   {
    "data": "16.05.2026 17:30",
    "rodada": "R12",
    "local": "FORA",
    "adv": "CF Montreal",
    "c_pro_ht": 1,
    "c_sof_ht": 4,
    "c_pro_2t": 2,
    "c_sof_2t": 12,
    "c_pro_ft": 3,
    "c_sof_ft": 16,
    "gols_pro_ht": 1,
    "gols_sof_ht": 0,
    "gols_pro_ft": 2,
    "gols_sof_ft": 0,
    "posse": 41,
    "fin": 11
   }
  ]
 },
 "Colorado Rapids": {
  "time": "Colorado Rapids",
  "n_jogos_total": 7,
  "n_casa": 2,
  "n_fora": 5,
  "volume": {
   "casa_pro_ft": 7,
   "casa_sof_ft": 1.5,
   "casa_total_ft": 8.5,
   "fora_pro_ft": 4.4,
   "fora_sof_ft": 5,
   "fora_total_ft": 9.4
  },
  "pos_gol_pro": null,
  "pos_gol_contra": {
   "n": 3,
   "c_2t_pro": 2.67,
   "c_2t_sof": 1.67,
   "diff": 1.0,
   "estilo": "EQUILIBRADO_REACAO"
  },
  "distribuicao_HT2T": {
   "pct_ht": 52.8,
   "categoria": "DISTRIBUIDO",
   "ht_pro_avg": 2.71,
   "t2_pro_avg": 2.43
  },
  "sangrador": {
   "sof_avg": 4,
   "posse_avg": 57.7,
   "tipo": "NORMAL"
  },
  "eficacia": {
   "cantos_por_gol": 7.2,
   "categoria": "ESTERIL",
   "total_gols": 5,
   "total_cantos": 36
  },
  "regime_atual": {
   "status": "⚪ NEUTRO",
   "obs": "Sem direção clara | sd 2.9 | desvio +1.6",
   "ultimos_jogos": [
    5,
    11,
    5,
    6
   ]
  },
  "historico": [
   {
    "data": "18.04.2026 17:30",
    "rodada": "R7",
    "local": "CASA",
    "adv": "Inter Miami",
    "c_pro_ht": 2,
    "c_sof_ht": 1,
    "c_pro_2t": 1,
    "c_sof_2t": 1,
    "c_pro_ft": 3,
    "c_sof_ft": 2,
    "gols_pro_ht": 0,
    "gols_sof_ht": 2,
    "gols_pro_ft": 2,
    "gols_sof_ft": 3,
    "posse": 62,
    "fin": 14
   },
   {
    "data": "22.04.2026 23:30",
    "rodada": "R8",
    "local": "FORA",
    "adv": "Los Angeles FC",
    "c_pro_ht": 3,
    "c_sof_ht": 0,
    "c_pro_2t": 0,
    "c_sof_2t": 4,
    "c_pro_ft": 3,
    "c_sof_ft": 4,
    "gols_pro_ht": 0,
    "gols_sof_ht": 0,
    "gols_pro_ft": 0,
    "gols_sof_ft": 0,
    "posse": 73,
    "fin": 6
   },
   {
    "data": "25.04.2026 23:30",
    "rodada": "R8",
    "local": "FORA",
    "adv": "Vancouver Whitecaps",
    "c_pro_ht": 1,
    "c_sof_ht": 5,
    "c_pro_2t": 2,
    "c_sof_2t": 3,
    "c_pro_ft": 3,
    "c_sof_ft": 8,
    "gols_pro_ht": 1,
    "gols_sof_ht": 2,
    "gols_pro_ft": 1,
    "gols_sof_ft": 3,
    "posse": 55,
    "fin": 13
   },
   {
    "data": "02.05.2026 21:30",
    "rodada": "R9",
    "local": "FORA",
    "adv": "Houston Dynamo",
    "c_pro_ht": 2,
    "c_sof_ht": 1,
    "c_pro_2t": 3,
    "c_sof_2t": 5,
    "c_pro_ft": 5,
    "c_sof_ft": 6,
    "gols_pro_ht": 0,
    "gols_sof_ht": 0,
    "gols_pro_ft": 0,
    "gols_sof_ft": 1,
    "posse": 61,
    "fin": 4
   },
   {
    "data": "09.05.2026 22:30",
    "rodada": "R10",
    "local": "CASA",
    "adv": "St. Louis City",
    "c_pro_ht": 6,
    "c_sof_ht": 0,
    "c_pro_2t": 5,
    "c_sof_2t": 1,
    "c_pro_ft": 11,
    "c_sof_ft": 1,
    "gols_pro_ht": 0,
    "gols_sof_ht": 1,
    "gols_pro_ft": 0,
    "gols_sof_ft": 1,
    "posse": 56,
    "fin": 10
   },
   {
    "data": "13.05.2026 21:30",
    "rodada": "R11",
    "local": "FORA",
    "adv": "Minnesota United",
    "c_pro_ht": 2,
    "c_sof_ht": 3,
    "c_pro_2t": 3,
    "c_sof_2t": 2,
    "c_pro_ft": 5,
    "c_sof_ft": 5,
    "gols_pro_ht": 1,
    "gols_sof_ht": 0,
    "gols_pro_ft": 1,
    "gols_sof_ft": 0,
    "posse": 45,
    "fin": 5
   },
   {
    "data": "16.05.2026 22:30",
    "rodada": "R12",
    "local": "FORA",
    "adv": "Real Salt Lake",
    "c_pro_ht": 3,
    "c_sof_ht": 1,
    "c_pro_2t": 3,
    "c_sof_2t": 1,
    "c_pro_ft": 6,
    "c_sof_ft": 2,
    "gols_pro_ht": 1,
    "gols_sof_ht": 1,
    "gols_pro_ft": 1,
    "gols_sof_ft": 2,
    "posse": 52,
    "fin": 8
   }
  ]
 },
 "Columbus Crew": {
  "time": "Columbus Crew",
  "n_jogos_total": 7,
  "n_casa": 3,
  "n_fora": 4,
  "volume": {
   "casa_pro_ft": 4.67,
   "casa_sof_ft": 3.67,
   "casa_total_ft": 8.33,
   "fora_pro_ft": 5.25,
   "fora_sof_ft": 3.25,
   "fora_total_ft": 8.5
  },
  "pos_gol_pro": {
   "n": 4,
   "c_2t_pro": 1.75,
   "c_2t_sof": 2,
   "diff": -0.25,
   "estilo": "EQUILIBRADO_POS_GOL"
  },
  "pos_gol_contra": {
   "n": 3,
   "c_2t_pro": 2.67,
   "c_2t_sof": 2,
   "diff": 0.67,
   "estilo": "EQUILIBRADO_REACAO"
  },
  "distribuicao_HT2T": {
   "pct_ht": 57.1,
   "categoria": "BLITZ_INICIAL",
   "ht_pro_avg": 2.86,
   "t2_pro_avg": 2.14
  },
  "sangrador": {
   "sof_avg": 3.43,
   "posse_avg": 61.1,
   "tipo": "DEFESA_SOLIDA"
  },
  "eficacia": {
   "cantos_por_gol": 3.89,
   "categoria": "NORMAL",
   "total_gols": 9,
   "total_cantos": 35
  },
  "regime_atual": {
   "status": "⚪ NEUTRO",
   "obs": "Sem direção clara | sd 2.5 | desvio -0.5",
   "ultimos_jogos": [
    4,
    8,
    2,
    4
   ]
  },
  "historico": [
   {
    "data": "12.04.2026 20:00",
    "rodada": "R7",
    "local": "CASA",
    "adv": "Orlando City",
    "c_pro_ht": 6,
    "c_sof_ht": 0,
    "c_pro_2t": 2,
    "c_sof_2t": 1,
    "c_pro_ft": 8,
    "c_sof_ft": 1,
    "gols_pro_ht": 0,
    "gols_sof_ht": 1,
    "gols_pro_ft": 1,
    "gols_sof_ft": 1,
    "posse": 65,
    "fin": 20
   },
   {
    "data": "18.04.2026 20:30",
    "rodada": "R7",
    "local": "FORA",
    "adv": "New England Revolution",
    "c_pro_ht": 4,
    "c_sof_ht": 2,
    "c_pro_2t": 3,
    "c_sof_2t": 1,
    "c_pro_ft": 7,
    "c_sof_ft": 3,
    "gols_pro_ht": 1,
    "gols_sof_ht": 0,
    "gols_pro_ft": 1,
    "gols_sof_ft": 2,
    "posse": 52,
    "fin": 11
   },
   {
    "data": "25.04.2026 20:30",
    "rodada": "R8",
    "local": "CASA",
    "adv": "Philadelphia Union",
    "c_pro_ht": 2,
    "c_sof_ht": 2,
    "c_pro_2t": 0,
    "c_sof_2t": 2,
    "c_pro_ft": 2,
    "c_sof_ft": 4,
    "gols_pro_ht": 2,
    "gols_sof_ht": 0,
    "gols_pro_ft": 2,
    "gols_sof_ft": 0,
    "posse": 56,
    "fin": 7
   },
   {
    "data": "02.05.2026 20:30",
    "rodada": "R9",
    "local": "CASA",
    "adv": "Minnesota United",
    "c_pro_ht": 2,
    "c_sof_ht": 3,
    "c_pro_2t": 2,
    "c_sof_2t": 3,
    "c_pro_ft": 4,
    "c_sof_ft": 6,
    "gols_pro_ht": 1,
    "gols_sof_ht": 0,
    "gols_pro_ft": 2,
    "gols_sof_ft": 3,
    "posse": 66,
    "fin": 13
   },
   {
    "data": "10.05.2026 17:30",
    "rodada": "R10",
    "local": "FORA",
    "adv": "New York City",
    "c_pro_ht": 4,
    "c_sof_ht": 0,
    "c_pro_2t": 4,
    "c_sof_2t": 3,
    "c_pro_ft": 8,
    "c_sof_ft": 3,
    "gols_pro_ht": 0,
    "gols_sof_ht": 2,
    "gols_pro_ft": 0,
    "gols_sof_ft": 3,
    "posse": 58,
    "fin": 11
   },
   {
    "data": "13.05.2026 20:30",
    "rodada": "R11",
    "local": "FORA",
    "adv": "New York Red Bulls",
    "c_pro_ht": 0,
    "c_sof_ht": 1,
    "c_pro_2t": 2,
    "c_sof_2t": 2,
    "c_pro_ft": 2,
    "c_sof_ft": 3,
    "gols_pro_ht": 1,
    "gols_sof_ht": 2,
    "gols_pro_ft": 2,
    "gols_sof_ft": 3,
    "posse": 69,
    "fin": 12
   },
   {
    "data": "16.05.2026 20:30",
    "rodada": "R12",
    "local": "FORA",
    "adv": "Philadelphia Union",
    "c_pro_ht": 2,
    "c_sof_ht": 2,
    "c_pro_2t": 2,
    "c_sof_2t": 2,
    "c_pro_ft": 4,
    "c_sof_ft": 4,
    "gols_pro_ht": 1,
    "gols_sof_ht": 0,
    "gols_pro_ft": 1,
    "gols_sof_ft": 1,
    "posse": 62,
    "fin": 5
   }
  ]
 },
 "DC United": {
  "time": "DC United",
  "n_jogos_total": 6,
  "n_casa": 3,
  "n_fora": 3,
  "volume": {
   "casa_pro_ft": 6.33,
   "casa_sof_ft": 8,
   "casa_total_ft": 14.33,
   "fora_pro_ft": 3.67,
   "fora_sof_ft": 9,
   "fora_total_ft": 12.67
  },
  "pos_gol_pro": {
   "n": 4,
   "c_2t_pro": 2.75,
   "c_2t_sof": 4,
   "diff": -1.25,
   "estilo": "RECUA_POS_GOL"
  },
  "pos_gol_contra": null,
  "distribuicao_HT2T": {
   "pct_ht": 56.7,
   "categoria": "BLITZ_INICIAL",
   "ht_pro_avg": 2.83,
   "t2_pro_avg": 2.17
  },
  "sangrador": {
   "sof_avg": 8.5,
   "posse_avg": 35.3,
   "tipo": "SANGRA_SEM_BOLA"
  },
  "eficacia": {
   "cantos_por_gol": 3.33,
   "categoria": "NORMAL",
   "total_gols": 9,
   "total_cantos": 30
  },
  "regime_atual": {
   "status": "⚪ NEUTRO",
   "obs": "Sem direção clara | sd 1.9 | desvio +0.5",
   "ultimos_jogos": [
    3,
    7,
    7,
    5
   ]
  },
  "historico": [
   {
    "data": "18.04.2026 20:30",
    "rodada": "R7",
    "local": "FORA",
    "adv": "Philadelphia Union",
    "c_pro_ht": 1,
    "c_sof_ht": 4,
    "c_pro_2t": 0,
    "c_sof_2t": 9,
    "c_pro_ft": 1,
    "c_sof_ft": 13,
    "gols_pro_ht": 0,
    "gols_sof_ht": 0,
    "gols_pro_ft": 0,
    "gols_sof_ft": 0,
    "posse": 38,
    "fin": 6
   },
   {
    "data": "25.04.2026 20:30",
    "rodada": "R8",
    "local": "CASA",
    "adv": "Orlando City",
    "c_pro_ht": 3,
    "c_sof_ht": 5,
    "c_pro_2t": 4,
    "c_sof_2t": 3,
    "c_pro_ft": 7,
    "c_sof_ft": 8,
    "gols_pro_ht": 1,
    "gols_sof_ht": 0,
    "gols_pro_ft": 3,
    "gols_sof_ft": 2,
    "posse": 38,
    "fin": 15
   },
   {
    "data": "03.05.2026 16:00",
    "rodada": "R9",
    "local": "FORA",
    "adv": "New York City",
    "c_pro_ht": 2,
    "c_sof_ht": 2,
    "c_pro_2t": 1,
    "c_sof_2t": 4,
    "c_pro_ft": 3,
    "c_sof_ft": 6,
    "gols_pro_ht": 1,
    "gols_sof_ht": 0,
    "gols_pro_ft": 2,
    "gols_sof_ft": 0,
    "posse": 27,
    "fin": 19
   },
   {
    "data": "09.05.2026 22:15",
    "rodada": "R10",
    "local": "FORA",
    "adv": "Nashville SC",
    "c_pro_ht": 5,
    "c_sof_ht": 4,
    "c_pro_2t": 2,
    "c_sof_2t": 4,
    "c_pro_ft": 7,
    "c_sof_ft": 8,
    "gols_pro_ht": 2,
    "gols_sof_ht": 0,
    "gols_pro_ft": 2,
    "gols_sof_ft": 2,
    "posse": 26,
    "fin": 12
   },
   {
    "data": "13.05.2026 20:30",
    "rodada": "R11",
    "local": "CASA",
    "adv": "Chicago Fire",
    "c_pro_ht": 3,
    "c_sof_ht": 3,
    "c_pro_2t": 4,
    "c_sof_2t": 5,
    "c_pro_ft": 7,
    "c_sof_ft": 8,
    "gols_pro_ht": 1,
    "gols_sof_ht": 0,
    "gols_pro_ft": 1,
    "gols_sof_ft": 3,
    "posse": 40,
    "fin": 13
   },
   {
    "data": "16.05.2026 20:30",
    "rodada": "R12",
    "local": "CASA",
    "adv": "St. Louis City",
    "c_pro_ht": 3,
    "c_sof_ht": 8,
    "c_pro_2t": 2,
    "c_sof_2t": 0,
    "c_pro_ft": 5,
    "c_sof_ft": 8,
    "gols_pro_ht": 0,
    "gols_sof_ht": 0,
    "gols_pro_ft": 1,
    "gols_sof_ft": 1,
    "posse": 43,
    "fin": 15
   }
  ]
 },
 "FC Cincinnati": {
  "time": "FC Cincinnati",
  "n_jogos_total": 6,
  "n_casa": 3,
  "n_fora": 3,
  "volume": {
   "casa_pro_ft": 4.67,
   "casa_sof_ft": 5.33,
   "casa_total_ft": 10.0,
   "fora_pro_ft": 2.33,
   "fora_sof_ft": 8,
   "fora_total_ft": 10.33
  },
  "pos_gol_pro": {
   "n": 2,
   "c_2t_pro": 1.5,
   "c_2t_sof": 4.5,
   "diff": -3.0,
   "estilo": "RECUA_POS_GOL"
  },
  "pos_gol_contra": null,
  "distribuicao_HT2T": {
   "pct_ht": 57.1,
   "categoria": "BLITZ_INICIAL",
   "ht_pro_avg": 2,
   "t2_pro_avg": 1.5
  },
  "sangrador": {
   "sof_avg": 6.67,
   "posse_avg": 47.3,
   "tipo": "SANGRA_SEM_BOLA"
  },
  "eficacia": {
   "cantos_por_gol": 1.31,
   "categoria": "CLINICA",
   "total_gols": 16,
   "total_cantos": 21
  },
  "regime_atual": {
   "status": "🟢 ATIVO_NEGATIVO",
   "obs": "Últimos 3+ jogos consistentemente baixa (1.4 sd) | desvio vs geral: -1.5",
   "ultimos_jogos": [
    1,
    4,
    1,
    2
   ]
  },
  "historico": [
   {
    "data": "18.04.2026 20:30",
    "rodada": "R7",
    "local": "CASA",
    "adv": "Chicago Fire",
    "c_pro_ht": 5,
    "c_sof_ht": 1,
    "c_pro_2t": 4,
    "c_sof_2t": 0,
    "c_pro_ft": 9,
    "c_sof_ft": 1,
    "gols_pro_ht": 1,
    "gols_sof_ht": 2,
    "gols_pro_ft": 3,
    "gols_sof_ft": 3,
    "posse": 55,
    "fin": 23
   },
   {
    "data": "25.04.2026 20:30",
    "rodada": "R8",
    "local": "CASA",
    "adv": "New York Red Bulls",
    "c_pro_ht": 3,
    "c_sof_ht": 2,
    "c_pro_2t": 1,
    "c_sof_2t": 5,
    "c_pro_ft": 4,
    "c_sof_ft": 7,
    "gols_pro_ht": 2,
    "gols_sof_ht": 0,
    "gols_pro_ft": 2,
    "gols_sof_ft": 0,
    "posse": 48,
    "fin": 15
   },
   {
    "data": "02.05.2026 21:30",
    "rodada": "R9",
    "local": "FORA",
    "adv": "Chicago Fire",
    "c_pro_ht": 0,
    "c_sof_ht": 3,
    "c_pro_2t": 1,
    "c_sof_2t": 7,
    "c_pro_ft": 1,
    "c_sof_ft": 10,
    "gols_pro_ht": 2,
    "gols_sof_ht": 2,
    "gols_pro_ft": 3,
    "gols_sof_ft": 2,
    "posse": 44,
    "fin": 10
   },
   {
    "data": "09.05.2026 20:30",
    "rodada": "R10",
    "local": "FORA",
    "adv": "Charlotte",
    "c_pro_ht": 2,
    "c_sof_ht": 3,
    "c_pro_2t": 2,
    "c_sof_2t": 4,
    "c_pro_ft": 4,
    "c_sof_ft": 7,
    "gols_pro_ht": 2,
    "gols_sof_ht": 0,
    "gols_pro_ft": 2,
    "gols_sof_ft": 2,
    "posse": 53,
    "fin": 13
   },
   {
    "data": "13.05.2026 20:30",
    "rodada": "R11",
    "local": "CASA",
    "adv": "Inter Miami",
    "c_pro_ht": 1,
    "c_sof_ht": 5,
    "c_pro_2t": 0,
    "c_sof_2t": 3,
    "c_pro_ft": 1,
    "c_sof_ft": 8,
    "gols_pro_ht": 1,
    "gols_sof_ht": 1,
    "gols_pro_ft": 3,
    "gols_sof_ft": 5,
    "posse": 47,
    "fin": 10
   },
   {
    "data": "16.05.2026 22:30",
    "rodada": "R12",
    "local": "FORA",
    "adv": "San Diego FC",
    "c_pro_ht": 1,
    "c_sof_ht": 3,
    "c_pro_2t": 1,
    "c_sof_2t": 4,
    "c_pro_ft": 2,
    "c_sof_ft": 7,
    "gols_pro_ht": 1,
    "gols_sof_ht": 1,
    "gols_pro_ft": 3,
    "gols_sof_ft": 3,
    "posse": 37,
    "fin": 8
   }
  ]
 },
 "FC Dallas": {
  "time": "FC Dallas",
  "n_jogos_total": 6,
  "n_casa": 3,
  "n_fora": 3,
  "volume": {
   "casa_pro_ft": 4.67,
   "casa_sof_ft": 5.33,
   "casa_total_ft": 10.0,
   "fora_pro_ft": 5,
   "fora_sof_ft": 8,
   "fora_total_ft": 13
  },
  "pos_gol_pro": null,
  "pos_gol_contra": {
   "n": 2,
   "c_2t_pro": 4,
   "c_2t_sof": 3,
   "diff": 1,
   "estilo": "REAGE_PRESSIONA"
  },
  "distribuicao_HT2T": {
   "pct_ht": 44.8,
   "categoria": "DISTRIBUIDO",
   "ht_pro_avg": 2.17,
   "t2_pro_avg": 2.67
  },
  "sangrador": {
   "sof_avg": 6.67,
   "posse_avg": 42,
   "tipo": "SANGRA_SEM_BOLA"
  },
  "eficacia": {
   "cantos_por_gol": 2.23,
   "categoria": "CLINICA",
   "total_gols": 13,
   "total_cantos": 29
  },
  "regime_atual": {
   "status": "⚪ NEUTRO",
   "obs": "Sem direção clara | sd 1.0 | desvio -0.3",
   "ultimos_jogos": [
    4,
    4,
    6,
    4
   ]
  },
  "historico": [
   {
    "data": "18.04.2026 21:30",
    "rodada": "R7",
    "local": "CASA",
    "adv": "Los Angeles Galaxy",
    "c_pro_ht": 1,
    "c_sof_ht": 0,
    "c_pro_2t": 3,
    "c_sof_2t": 3,
    "c_pro_ft": 4,
    "c_sof_ft": 3,
    "gols_pro_ht": 2,
    "gols_sof_ht": 2,
    "gols_pro_ft": 2,
    "gols_sof_ft": 2,
    "posse": 47,
    "fin": 13
   },
   {
    "data": "25.04.2026 23:30",
    "rodada": "R8",
    "local": "FORA",
    "adv": "Seattle Sounders",
    "c_pro_ht": 3,
    "c_sof_ht": 2,
    "c_pro_2t": 4,
    "c_sof_2t": 2,
    "c_pro_ft": 7,
    "c_sof_ft": 4,
    "gols_pro_ht": 1,
    "gols_sof_ht": 2,
    "gols_pro_ft": 1,
    "gols_sof_ft": 2,
    "posse": 42,
    "fin": 12
   },
   {
    "data": "02.05.2026 20:30",
    "rodada": "R9",
    "local": "FORA",
    "adv": "New York Red Bulls",
    "c_pro_ht": 2,
    "c_sof_ht": 5,
    "c_pro_2t": 2,
    "c_sof_2t": 3,
    "c_pro_ft": 4,
    "c_sof_ft": 8,
    "gols_pro_ht": 0,
    "gols_sof_ht": 0,
    "gols_pro_ft": 2,
    "gols_sof_ft": 0,
    "posse": 42,
    "fin": 12
   },
   {
    "data": "09.05.2026 21:30",
    "rodada": "R10",
    "local": "CASA",
    "adv": "Real Salt Lake",
    "c_pro_ht": 2,
    "c_sof_ht": 5,
    "c_pro_2t": 2,
    "c_sof_2t": 2,
    "c_pro_ft": 4,
    "c_sof_ft": 7,
    "gols_pro_ht": 2,
    "gols_sof_ht": 0,
    "gols_pro_ft": 3,
    "gols_sof_ft": 1,
    "posse": 27,
    "fin": 11
   },
   {
    "data": "13.05.2026 21:30",
    "rodada": "R11",
    "local": "CASA",
    "adv": "Vancouver Whitecaps",
    "c_pro_ht": 2,
    "c_sof_ht": 2,
    "c_pro_2t": 4,
    "c_sof_2t": 4,
    "c_pro_ft": 6,
    "c_sof_ft": 6,
    "gols_pro_ht": 1,
    "gols_sof_ht": 2,
    "gols_pro_ft": 2,
    "gols_sof_ft": 3,
    "posse": 49,
    "fin": 8
   },
   {
    "data": "16.05.2026 23:30",
    "rodada": "R12",
    "local": "FORA",
    "adv": "San Jose Earthquakes",
    "c_pro_ht": 3,
    "c_sof_ht": 2,
    "c_pro_2t": 1,
    "c_sof_2t": 10,
    "c_pro_ft": 4,
    "c_sof_ft": 12,
    "gols_pro_ht": 1,
    "gols_sof_ht": 1,
    "gols_pro_ft": 3,
    "gols_sof_ft": 2,
    "posse": 45,
    "fin": 16
   }
  ]
 },
 "Houston Dynamo": {
  "time": "Houston Dynamo",
  "n_jogos_total": 6,
  "n_casa": 2,
  "n_fora": 4,
  "volume": {
   "casa_pro_ft": 5,
   "casa_sof_ft": 4,
   "casa_total_ft": 9,
   "fora_pro_ft": 3,
   "fora_sof_ft": 5.25,
   "fora_total_ft": 8.25
  },
  "pos_gol_pro": null,
  "pos_gol_contra": null,
  "distribuicao_HT2T": {
   "pct_ht": 45.5,
   "categoria": "DISTRIBUIDO",
   "ht_pro_avg": 1.67,
   "t2_pro_avg": 2
  },
  "sangrador": {
   "sof_avg": 4.83,
   "posse_avg": 44.5,
   "tipo": "NORMAL"
  },
  "eficacia": {
   "cantos_por_gol": 3.14,
   "categoria": "NORMAL",
   "total_gols": 7,
   "total_cantos": 22
  },
  "regime_atual": {
   "status": "⚪ NEUTRO",
   "obs": "Sem direção clara | sd 2.1 | desvio -0.2",
   "ultimos_jogos": [
    6,
    3,
    1,
    4
   ]
  },
  "historico": [
   {
    "data": "18.04.2026 20:30",
    "rodada": "R7",
    "local": "FORA",
    "adv": "Orlando City",
    "c_pro_ht": 3,
    "c_sof_ht": 3,
    "c_pro_2t": 0,
    "c_sof_2t": 1,
    "c_pro_ft": 3,
    "c_sof_ft": 4,
    "gols_pro_ht": 0,
    "gols_sof_ht": 0,
    "gols_pro_ft": 1,
    "gols_sof_ft": 0,
    "posse": 40,
    "fin": 18
   },
   {
    "data": "25.04.2026 21:30",
    "rodada": "R8",
    "local": "FORA",
    "adv": "Austin FC",
    "c_pro_ht": 3,
    "c_sof_ht": 1,
    "c_pro_2t": 2,
    "c_sof_2t": 2,
    "c_pro_ft": 5,
    "c_sof_ft": 3,
    "gols_pro_ht": 0,
    "gols_sof_ht": 2,
    "gols_pro_ft": 0,
    "gols_sof_ft": 2,
    "posse": 55,
    "fin": 11
   },
   {
    "data": "02.05.2026 21:30",
    "rodada": "R9",
    "local": "CASA",
    "adv": "Colorado Rapids",
    "c_pro_ht": 1,
    "c_sof_ht": 2,
    "c_pro_2t": 5,
    "c_sof_2t": 3,
    "c_pro_ft": 6,
    "c_sof_ft": 5,
    "gols_pro_ht": 0,
    "gols_sof_ht": 0,
    "gols_pro_ft": 1,
    "gols_sof_ft": 0,
    "posse": 39,
    "fin": 9
   },
   {
    "data": "10.05.2026 22:00",
    "rodada": "R10",
    "local": "FORA",
    "adv": "Los Angeles FC",
    "c_pro_ht": 0,
    "c_sof_ht": 6,
    "c_pro_2t": 3,
    "c_sof_2t": 4,
    "c_pro_ft": 3,
    "c_sof_ft": 10,
    "gols_pro_ht": 2,
    "gols_sof_ht": 1,
    "gols_pro_ft": 4,
    "gols_sof_ft": 1,
    "posse": 33,
    "fin": 12
   },
   {
    "data": "13.05.2026 22:30",
    "rodada": "R11",
    "local": "FORA",
    "adv": "Real Salt Lake",
    "c_pro_ht": 1,
    "c_sof_ht": 2,
    "c_pro_2t": 0,
    "c_sof_2t": 2,
    "c_pro_ft": 1,
    "c_sof_ft": 4,
    "gols_pro_ht": 0,
    "gols_sof_ht": 0,
    "gols_pro_ft": 0,
    "gols_sof_ft": 3,
    "posse": 47,
    "fin": 15
   },
   {
    "data": "16.05.2026 21:30",
    "rodada": "R12",
    "local": "CASA",
    "adv": "Vancouver Whitecaps",
    "c_pro_ht": 2,
    "c_sof_ht": 1,
    "c_pro_2t": 2,
    "c_sof_2t": 2,
    "c_pro_ft": 4,
    "c_sof_ft": 3,
    "gols_pro_ht": 0,
    "gols_sof_ht": 0,
    "gols_pro_ft": 1,
    "gols_sof_ft": 0,
    "posse": 53,
    "fin": 14
   }
  ]
 },
 "Inter Miami": {
  "time": "Inter Miami",
  "n_jogos_total": 5,
  "n_casa": 2,
  "n_fora": 3,
  "volume": {
   "casa_pro_ft": 8.5,
   "casa_sof_ft": 1.5,
   "casa_total_ft": 10.0,
   "fora_pro_ft": 4.67,
   "fora_sof_ft": 2.67,
   "fora_total_ft": 7.33
  },
  "pos_gol_pro": {
   "n": 3,
   "c_2t_pro": 2.33,
   "c_2t_sof": 1.67,
   "diff": 0.67,
   "estilo": "EQUILIBRADO_POS_GOL"
  },
  "pos_gol_contra": null,
  "distribuicao_HT2T": {
   "pct_ht": 58.1,
   "categoria": "BLITZ_INICIAL",
   "ht_pro_avg": 3.6,
   "t2_pro_avg": 2.6
  },
  "sangrador": {
   "sof_avg": 2.2,
   "posse_avg": 56.6,
   "tipo": "DEFESA_SOLIDA"
  },
  "eficacia": {
   "cantos_por_gol": 1.94,
   "categoria": "CLINICA",
   "total_gols": 16,
   "total_cantos": 31
  },
  "regime_atual": {
   "status": "⚪ NEUTRO",
   "obs": "Sem direção clara | sd 2.5 | desvio +1.0",
   "ultimos_jogos": [
    7,
    10,
    4,
    8
   ]
  },
  "historico": [
   {
    "data": "18.04.2026 17:30",
    "rodada": "R7",
    "local": "FORA",
    "adv": "Colorado Rapids",
    "c_pro_ht": 1,
    "c_sof_ht": 2,
    "c_pro_2t": 1,
    "c_sof_2t": 1,
    "c_pro_ft": 2,
    "c_sof_ft": 3,
    "gols_pro_ht": 2,
    "gols_sof_ht": 0,
    "gols_pro_ft": 3,
    "gols_sof_ft": 2,
    "posse": 38,
    "fin": 6
   },
   {
    "data": "25.04.2026 20:30",
    "rodada": "R8",
    "local": "CASA",
    "adv": "New England Revolution",
    "c_pro_ht": 4,
    "c_sof_ht": 0,
    "c_pro_2t": 3,
    "c_sof_2t": 1,
    "c_pro_ft": 7,
    "c_sof_ft": 1,
    "gols_pro_ht": 0,
    "gols_sof_ht": 0,
    "gols_pro_ft": 1,
    "gols_sof_ft": 1,
    "posse": 68,
    "fin": 18
   },
   {
    "data": "02.05.2026 20:15",
    "rodada": "R9",
    "local": "CASA",
    "adv": "Orlando City",
    "c_pro_ht": 8,
    "c_sof_ht": 0,
    "c_pro_2t": 2,
    "c_sof_2t": 2,
    "c_pro_ft": 10,
    "c_sof_ft": 2,
    "gols_pro_ht": 3,
    "gols_sof_ht": 1,
    "gols_pro_ft": 3,
    "gols_sof_ft": 4,
    "posse": 64,
    "fin": 26
   },
   {
    "data": "09.05.2026 14:00",
    "rodada": "R10",
    "local": "FORA",
    "adv": "Toronto FC",
    "c_pro_ht": 0,
    "c_sof_ht": 2,
    "c_pro_2t": 4,
    "c_sof_2t": 2,
    "c_pro_ft": 4,
    "c_sof_ft": 4,
    "gols_pro_ht": 1,
    "gols_sof_ht": 0,
    "gols_pro_ft": 4,
    "gols_sof_ft": 2,
    "posse": 60,
    "fin": 11
   },
   {
    "data": "13.05.2026 20:30",
    "rodada": "R11",
    "local": "FORA",
    "adv": "FC Cincinnati",
    "c_pro_ht": 5,
    "c_sof_ht": 1,
    "c_pro_2t": 3,
    "c_sof_2t": 0,
    "c_pro_ft": 8,
    "c_sof_ft": 1,
    "gols_pro_ht": 1,
    "gols_sof_ht": 1,
    "gols_pro_ft": 5,
    "gols_sof_ft": 3,
    "posse": 53,
    "fin": 17
   }
  ]
 },
 "Los Angeles FC": {
  "time": "Los Angeles FC",
  "n_jogos_total": 6,
  "n_casa": 3,
  "n_fora": 3,
  "volume": {
   "casa_pro_ft": 6.33,
   "casa_sof_ft": 3,
   "casa_total_ft": 9.33,
   "fora_pro_ft": 4.33,
   "fora_sof_ft": 5,
   "fora_total_ft": 9.33
  },
  "pos_gol_pro": null,
  "pos_gol_contra": {
   "n": 3,
   "c_2t_pro": 4.33,
   "c_2t_sof": 1,
   "diff": 3.33,
   "estilo": "REAGE_PRESSIONA"
  },
  "distribuicao_HT2T": {
   "pct_ht": 28.1,
   "categoria": "ASFIXIA_FINAL",
   "ht_pro_avg": 1.5,
   "t2_pro_avg": 3.83
  },
  "sangrador": {
   "sof_avg": 4,
   "posse_avg": 48.5,
   "tipo": "NORMAL"
  },
  "eficacia": {
   "cantos_por_gol": 5.33,
   "categoria": "ESTERIL",
   "total_gols": 6,
   "total_cantos": 32
  },
  "regime_atual": {
   "status": "🔴 QUEBRADO",
   "obs": "Alta variância nos últimos jogos (sd 3.9) | sem padrão claro",
   "ultimos_jogos": [
    2,
    3,
    10,
    8
   ]
  },
  "historico": [
   {
    "data": "19.04.2026 20:00",
    "rodada": "R7",
    "local": "CASA",
    "adv": "San Jose Earthquakes",
    "c_pro_ht": 1,
    "c_sof_ht": 1,
    "c_pro_2t": 4,
    "c_sof_2t": 2,
    "c_pro_ft": 5,
    "c_sof_ft": 3,
    "gols_pro_ht": 0,
    "gols_sof_ht": 0,
    "gols_pro_ft": 1,
    "gols_sof_ft": 4,
    "posse": 53,
    "fin": 16
   },
   {
    "data": "22.04.2026 23:30",
    "rodada": "R8",
    "local": "CASA",
    "adv": "Colorado Rapids",
    "c_pro_ht": 0,
    "c_sof_ht": 3,
    "c_pro_2t": 4,
    "c_sof_2t": 0,
    "c_pro_ft": 4,
    "c_sof_ft": 3,
    "gols_pro_ht": 0,
    "gols_sof_ht": 0,
    "gols_pro_ft": 0,
    "gols_sof_ft": 0,
    "posse": 27,
    "fin": 5
   },
   {
    "data": "25.04.2026 17:45",
    "rodada": "R8",
    "local": "FORA",
    "adv": "Minnesota United",
    "c_pro_ht": 0,
    "c_sof_ht": 5,
    "c_pro_2t": 2,
    "c_sof_2t": 6,
    "c_pro_ft": 2,
    "c_sof_ft": 11,
    "gols_pro_ht": 1,
    "gols_sof_ht": 0,
    "gols_pro_ft": 1,
    "gols_sof_ft": 0,
    "posse": 38,
    "fin": 7
   },
   {
    "data": "02.05.2026 22:30",
    "rodada": "R9",
    "local": "FORA",
    "adv": "San Diego FC",
    "c_pro_ht": 0,
    "c_sof_ht": 2,
    "c_pro_2t": 3,
    "c_sof_2t": 0,
    "c_pro_ft": 3,
    "c_sof_ft": 2,
    "gols_pro_ht": 0,
    "gols_sof_ht": 1,
    "gols_pro_ft": 2,
    "gols_sof_ft": 2,
    "posse": 44,
    "fin": 9
   },
   {
    "data": "10.05.2026 22:00",
    "rodada": "R10",
    "local": "CASA",
    "adv": "Houston Dynamo",
    "c_pro_ht": 6,
    "c_sof_ht": 0,
    "c_pro_2t": 4,
    "c_sof_2t": 3,
    "c_pro_ft": 10,
    "c_sof_ft": 3,
    "gols_pro_ht": 1,
    "gols_sof_ht": 2,
    "gols_pro_ft": 1,
    "gols_sof_ft": 4,
    "posse": 67,
    "fin": 19
   },
   {
    "data": "13.05.2026 21:30",
    "rodada": "R11",
    "local": "FORA",
    "adv": "St. Louis City",
    "c_pro_ht": 2,
    "c_sof_ht": 2,
    "c_pro_2t": 6,
    "c_sof_2t": 0,
    "c_pro_ft": 8,
    "c_sof_ft": 2,
    "gols_pro_ht": 0,
    "gols_sof_ht": 1,
    "gols_pro_ft": 1,
    "gols_sof_ft": 2,
    "posse": 62,
    "fin": 16
   }
  ]
 },
 "Los Angeles Galaxy": {
  "time": "Los Angeles Galaxy",
  "n_jogos_total": 6,
  "n_casa": 2,
  "n_fora": 4,
  "volume": {
   "casa_pro_ft": 4,
   "casa_sof_ft": 1,
   "casa_total_ft": 5,
   "fora_pro_ft": 4.25,
   "fora_sof_ft": 4.75,
   "fora_total_ft": 9.0
  },
  "pos_gol_pro": null,
  "pos_gol_contra": null,
  "distribuicao_HT2T": {
   "pct_ht": 52.0,
   "categoria": "DISTRIBUIDO",
   "ht_pro_avg": 2.17,
   "t2_pro_avg": 2
  },
  "sangrador": {
   "sof_avg": 3.5,
   "posse_avg": 46.5,
   "tipo": "DEFESA_SOLIDA"
  },
  "eficacia": {
   "cantos_por_gol": 2.5,
   "categoria": "CLINICA",
   "total_gols": 10,
   "total_cantos": 25
  },
  "regime_atual": {
   "status": "🔴 QUEBRADO",
   "obs": "Alta variância nos últimos jogos (sd 3.4) | sem padrão claro",
   "ultimos_jogos": [
    1,
    5,
    8,
    1
   ]
  },
  "historico": [
   {
    "data": "18.04.2026 21:30",
    "rodada": "R7",
    "local": "FORA",
    "adv": "FC Dallas",
    "c_pro_ht": 0,
    "c_sof_ht": 1,
    "c_pro_2t": 3,
    "c_sof_2t": 3,
    "c_pro_ft": 3,
    "c_sof_ft": 4,
    "gols_pro_ht": 2,
    "gols_sof_ht": 2,
    "gols_pro_ft": 2,
    "gols_sof_ft": 2,
    "posse": 53,
    "fin": 9
   },
   {
    "data": "26.04.2026 20:00",
    "rodada": "R8",
    "local": "CASA",
    "adv": "Real Salt Lake",
    "c_pro_ht": 5,
    "c_sof_ht": 0,
    "c_pro_2t": 2,
    "c_sof_2t": 0,
    "c_pro_ft": 7,
    "c_sof_ft": 0,
    "gols_pro_ht": 1,
    "gols_sof_ht": 1,
    "gols_pro_ft": 2,
    "gols_sof_ft": 1,
    "posse": 39,
    "fin": 16
   },
   {
    "data": "02.05.2026 23:30",
    "rodada": "R9",
    "local": "CASA",
    "adv": "Vancouver Whitecaps",
    "c_pro_ht": 0,
    "c_sof_ht": 2,
    "c_pro_2t": 1,
    "c_sof_2t": 0,
    "c_pro_ft": 1,
    "c_sof_ft": 2,
    "gols_pro_ht": 0,
    "gols_sof_ht": 0,
    "gols_pro_ft": 1,
    "gols_sof_ft": 1,
    "posse": 38,
    "fin": 7
   },
   {
    "data": "09.05.2026 20:30",
    "rodada": "R10",
    "local": "FORA",
    "adv": "Atlanta Utd",
    "c_pro_ht": 1,
    "c_sof_ht": 4,
    "c_pro_2t": 4,
    "c_sof_2t": 2,
    "c_pro_ft": 5,
    "c_sof_ft": 6,
    "gols_pro_ht": 0,
    "gols_sof_ht": 0,
    "gols_pro_ft": 2,
    "gols_sof_ft": 1,
    "posse": 47,
    "fin": 10
   },
   {
    "data": "13.05.2026 21:30",
    "rodada": "R11",
    "local": "FORA",
    "adv": "Sporting Kansas City",
    "c_pro_ht": 6,
    "c_sof_ht": 3,
    "c_pro_2t": 2,
    "c_sof_2t": 1,
    "c_pro_ft": 8,
    "c_sof_ft": 4,
    "gols_pro_ht": 0,
    "gols_sof_ht": 2,
    "gols_pro_ft": 1,
    "gols_sof_ft": 3,
    "posse": 60,
    "fin": 18
   },
   {
    "data": "16.05.2026 22:15",
    "rodada": "R12",
    "local": "FORA",
    "adv": "Seattle Sounders",
    "c_pro_ht": 1,
    "c_sof_ht": 0,
    "c_pro_2t": 0,
    "c_sof_2t": 5,
    "c_pro_ft": 1,
    "c_sof_ft": 5,
    "gols_pro_ht": 1,
    "gols_sof_ht": 0,
    "gols_pro_ft": 2,
    "gols_sof_ft": 0,
    "posse": 42,
    "fin": 9
   }
  ]
 },
 "Minnesota United": {
  "time": "Minnesota United",
  "n_jogos_total": 7,
  "n_casa": 4,
  "n_fora": 3,
  "volume": {
   "casa_pro_ft": 5.5,
   "casa_sof_ft": 3.75,
   "casa_total_ft": 9.25,
   "fora_pro_ft": 7.33,
   "fora_sof_ft": 5.33,
   "fora_total_ft": 12.67
  },
  "pos_gol_pro": {
   "n": 2,
   "c_2t_pro": 3.5,
   "c_2t_sof": 2.5,
   "diff": 1.0,
   "estilo": "PRESSIONA_POS_GOL"
  },
  "pos_gol_contra": {
   "n": 4,
   "c_2t_pro": 3,
   "c_2t_sof": 2,
   "diff": 1,
   "estilo": "REAGE_PRESSIONA"
  },
  "distribuicao_HT2T": {
   "pct_ht": 43.2,
   "categoria": "DISTRIBUIDO",
   "ht_pro_avg": 2.71,
   "t2_pro_avg": 3.57
  },
  "sangrador": {
   "sof_avg": 4.43,
   "posse_avg": 48.6,
   "tipo": "NORMAL"
  },
  "eficacia": {
   "cantos_por_gol": 4.4,
   "categoria": "NORMAL",
   "total_gols": 10,
   "total_cantos": 44
  },
  "regime_atual": {
   "status": "🔴 QUEBRADO",
   "obs": "Alta variância nos últimos jogos (sd 3.4) | sem padrão claro",
   "ultimos_jogos": [
    6,
    3,
    5,
    11
   ]
  },
  "historico": [
   {
    "data": "11.04.2026 23:30",
    "rodada": "R7",
    "local": "FORA",
    "adv": "San Diego FC",
    "c_pro_ht": 0,
    "c_sof_ht": 1,
    "c_pro_2t": 5,
    "c_sof_2t": 3,
    "c_pro_ft": 5,
    "c_sof_ft": 4,
    "gols_pro_ht": 2,
    "gols_sof_ht": 1,
    "gols_pro_ft": 2,
    "gols_sof_ft": 1,
    "posse": 36,
    "fin": 21
   },
   {
    "data": "18.04.2026 21:30",
    "rodada": "R7",
    "local": "CASA",
    "adv": "Portland Timbers",
    "c_pro_ht": 1,
    "c_sof_ht": 2,
    "c_pro_2t": 2,
    "c_sof_2t": 2,
    "c_pro_ft": 3,
    "c_sof_ft": 4,
    "gols_pro_ht": 1,
    "gols_sof_ht": 0,
    "gols_pro_ft": 2,
    "gols_sof_ft": 0,
    "posse": 44,
    "fin": 17
   },
   {
    "data": "25.04.2026 17:45",
    "rodada": "R8",
    "local": "CASA",
    "adv": "Los Angeles FC",
    "c_pro_ht": 5,
    "c_sof_ht": 0,
    "c_pro_2t": 6,
    "c_sof_2t": 2,
    "c_pro_ft": 11,
    "c_sof_ft": 2,
    "gols_pro_ht": 0,
    "gols_sof_ht": 1,
    "gols_pro_ft": 0,
    "gols_sof_ft": 1,
    "posse": 62,
    "fin": 23
   },
   {
    "data": "02.05.2026 20:30",
    "rodada": "R9",
    "local": "FORA",
    "adv": "Columbus Crew",
    "c_pro_ht": 3,
    "c_sof_ht": 2,
    "c_pro_2t": 3,
    "c_sof_2t": 2,
    "c_pro_ft": 6,
    "c_sof_ft": 4,
    "gols_pro_ht": 0,
    "gols_sof_ht": 1,
    "gols_pro_ft": 3,
    "gols_sof_ft": 2,
    "posse": 34,
    "fin": 12
   },
   {
    "data": "10.05.2026 20:00",
    "rodada": "R10",
    "local": "CASA",
    "adv": "Austin FC",
    "c_pro_ht": 2,
    "c_sof_ht": 3,
    "c_pro_2t": 1,
    "c_sof_2t": 1,
    "c_pro_ft": 3,
    "c_sof_ft": 4,
    "gols_pro_ht": 0,
    "gols_sof_ht": 1,
    "gols_pro_ft": 2,
    "gols_sof_ft": 2,
    "posse": 55,
    "fin": 18
   },
   {
    "data": "13.05.2026 21:30",
    "rodada": "R11",
    "local": "CASA",
    "adv": "Colorado Rapids",
    "c_pro_ht": 3,
    "c_sof_ht": 2,
    "c_pro_2t": 2,
    "c_sof_2t": 3,
    "c_pro_ft": 5,
    "c_sof_ft": 5,
    "gols_pro_ht": 0,
    "gols_sof_ht": 1,
    "gols_pro_ft": 0,
    "gols_sof_ft": 1,
    "posse": 55,
    "fin": 12
   },
   {
    "data": "16.05.2026 20:30",
    "rodada": "R12",
    "local": "FORA",
    "adv": "New England Revolution",
    "c_pro_ht": 5,
    "c_sof_ht": 4,
    "c_pro_2t": 6,
    "c_sof_2t": 4,
    "c_pro_ft": 11,
    "c_sof_ft": 8,
    "gols_pro_ht": 1,
    "gols_sof_ht": 1,
    "gols_pro_ft": 1,
    "gols_sof_ft": 2,
    "posse": 54,
    "fin": 12
   }
  ]
 },
 "Nashville SC": {
  "time": "Nashville SC",
  "n_jogos_total": 5,
  "n_casa": 2,
  "n_fora": 3,
  "volume": {
   "casa_pro_ft": 7,
   "casa_sof_ft": 5.5,
   "casa_total_ft": 12.5,
   "fora_pro_ft": 5.33,
   "fora_sof_ft": 5.33,
   "fora_total_ft": 10.67
  },
  "pos_gol_pro": {
   "n": 2,
   "c_2t_pro": 3.5,
   "c_2t_sof": 2.5,
   "diff": 1.0,
   "estilo": "PRESSIONA_POS_GOL"
  },
  "pos_gol_contra": null,
  "distribuicao_HT2T": {
   "pct_ht": 46.7,
   "categoria": "DISTRIBUIDO",
   "ht_pro_avg": 2.8,
   "t2_pro_avg": 3.2
  },
  "sangrador": {
   "sof_avg": 5.4,
   "posse_avg": 56.4,
   "tipo": "NORMAL"
  },
  "eficacia": {
   "cantos_por_gol": 2.73,
   "categoria": "CLINICA",
   "total_gols": 11,
   "total_cantos": 30
  },
  "regime_atual": {
   "status": "⚪ NEUTRO",
   "obs": "Sem direção clara | sd 2.6 | desvio -0.2",
   "ultimos_jogos": [
    6,
    2,
    8,
    7
   ]
  },
  "historico": [
   {
    "data": "18.04.2026 20:30",
    "rodada": "R7",
    "local": "FORA",
    "adv": "Atlanta Utd",
    "c_pro_ht": 4,
    "c_sof_ht": 1,
    "c_pro_2t": 3,
    "c_sof_2t": 4,
    "c_pro_ft": 7,
    "c_sof_ft": 5,
    "gols_pro_ht": 0,
    "gols_sof_ht": 0,
    "gols_pro_ft": 2,
    "gols_sof_ft": 0,
    "posse": 45,
    "fin": 17
   },
   {
    "data": "25.04.2026 21:30",
    "rodada": "R8",
    "local": "CASA",
    "adv": "Charlotte",
    "c_pro_ht": 4,
    "c_sof_ht": 0,
    "c_pro_2t": 2,
    "c_sof_2t": 4,
    "c_pro_ft": 6,
    "c_sof_ft": 4,
    "gols_pro_ht": 2,
    "gols_sof_ht": 1,
    "gols_pro_ft": 4,
    "gols_sof_ft": 2,
    "posse": 61,
    "fin": 13
   },
   {
    "data": "02.05.2026 20:30",
    "rodada": "R9",
    "local": "FORA",
    "adv": "Philadelphia Union",
    "c_pro_ht": 0,
    "c_sof_ht": 2,
    "c_pro_2t": 2,
    "c_sof_2t": 3,
    "c_pro_ft": 2,
    "c_sof_ft": 5,
    "gols_pro_ht": 0,
    "gols_sof_ht": 0,
    "gols_pro_ft": 0,
    "gols_sof_ft": 0,
    "posse": 54,
    "fin": 8
   },
   {
    "data": "09.05.2026 22:15",
    "rodada": "R10",
    "local": "CASA",
    "adv": "DC United",
    "c_pro_ht": 4,
    "c_sof_ht": 5,
    "c_pro_2t": 4,
    "c_sof_2t": 2,
    "c_pro_ft": 8,
    "c_sof_ft": 7,
    "gols_pro_ht": 0,
    "gols_sof_ht": 2,
    "gols_pro_ft": 2,
    "gols_sof_ft": 2,
    "posse": 74,
    "fin": 16
   },
   {
    "data": "13.05.2026 20:30",
    "rodada": "R11",
    "local": "FORA",
    "adv": "New England Revolution",
    "c_pro_ht": 2,
    "c_sof_ht": 5,
    "c_pro_2t": 5,
    "c_sof_2t": 1,
    "c_pro_ft": 7,
    "c_sof_ft": 6,
    "gols_pro_ht": 2,
    "gols_sof_ht": 0,
    "gols_pro_ft": 3,
    "gols_sof_ft": 0,
    "posse": 48,
    "fin": 8
   }
  ]
 },
 "New England Revolution": {
  "time": "New England Revolution",
  "n_jogos_total": 6,
  "n_casa": 5,
  "n_fora": 1,
  "volume": {
   "casa_pro_ft": 5.8,
   "casa_sof_ft": 6.6,
   "casa_total_ft": 12.4,
   "fora_pro_ft": 1,
   "fora_sof_ft": 7,
   "fora_total_ft": 8
  },
  "pos_gol_pro": null,
  "pos_gol_contra": {
   "n": 3,
   "c_2t_pro": 2,
   "c_2t_sof": 2.67,
   "diff": -0.67,
   "estilo": "EQUILIBRADO_REACAO"
  },
  "distribuicao_HT2T": {
   "pct_ht": 60.0,
   "categoria": "BLITZ_INICIAL",
   "ht_pro_avg": 3,
   "t2_pro_avg": 2
  },
  "sangrador": {
   "sof_avg": 6.67,
   "posse_avg": 49,
   "tipo": "SANGRA_SEM_BOLA"
  },
  "eficacia": {
   "cantos_por_gol": 3.75,
   "categoria": "NORMAL",
   "total_gols": 8,
   "total_cantos": 30
  },
  "regime_atual": {
   "status": "⚪ NEUTRO",
   "obs": "Sem direção clara | sd 2.6 | desvio +1.5",
   "ultimos_jogos": [
    3,
    9,
    6,
    8
   ]
  },
  "historico": [
   {
    "data": "18.04.2026 20:30",
    "rodada": "R7",
    "local": "CASA",
    "adv": "Columbus Crew",
    "c_pro_ht": 2,
    "c_sof_ht": 4,
    "c_pro_2t": 1,
    "c_sof_2t": 3,
    "c_pro_ft": 3,
    "c_sof_ft": 7,
    "gols_pro_ht": 0,
    "gols_sof_ht": 1,
    "gols_pro_ft": 2,
    "gols_sof_ft": 1,
    "posse": 48,
    "fin": 10
   },
   {
    "data": "25.04.2026 20:30",
    "rodada": "R8",
    "local": "FORA",
    "adv": "Inter Miami",
    "c_pro_ht": 0,
    "c_sof_ht": 4,
    "c_pro_2t": 1,
    "c_sof_2t": 3,
    "c_pro_ft": 1,
    "c_sof_ft": 7,
    "gols_pro_ht": 0,
    "gols_sof_ht": 0,
    "gols_pro_ft": 1,
    "gols_sof_ft": 1,
    "posse": 32,
    "fin": 16
   },
   {
    "data": "02.05.2026 20:30",
    "rodada": "R9",
    "local": "CASA",
    "adv": "Charlotte",
    "c_pro_ht": 2,
    "c_sof_ht": 3,
    "c_pro_2t": 1,
    "c_sof_2t": 2,
    "c_pro_ft": 3,
    "c_sof_ft": 5,
    "gols_pro_ht": 0,
    "gols_sof_ht": 0,
    "gols_pro_ft": 1,
    "gols_sof_ft": 0,
    "posse": 55,
    "fin": 14
   },
   {
    "data": "09.05.2026 20:30",
    "rodada": "R10",
    "local": "CASA",
    "adv": "Philadelphia Union",
    "c_pro_ht": 5,
    "c_sof_ht": 3,
    "c_pro_2t": 4,
    "c_sof_2t": 0,
    "c_pro_ft": 9,
    "c_sof_ft": 3,
    "gols_pro_ht": 0,
    "gols_sof_ht": 1,
    "gols_pro_ft": 2,
    "gols_sof_ft": 1,
    "posse": 61,
    "fin": 10
   },
   {
    "data": "13.05.2026 20:30",
    "rodada": "R11",
    "local": "CASA",
    "adv": "Nashville SC",
    "c_pro_ht": 5,
    "c_sof_ht": 2,
    "c_pro_2t": 1,
    "c_sof_2t": 5,
    "c_pro_ft": 6,
    "c_sof_ft": 7,
    "gols_pro_ht": 0,
    "gols_sof_ht": 2,
    "gols_pro_ft": 0,
    "gols_sof_ft": 3,
    "posse": 52,
    "fin": 8
   },
   {
    "data": "16.05.2026 20:30",
    "rodada": "R12",
    "local": "CASA",
    "adv": "Minnesota United",
    "c_pro_ht": 4,
    "c_sof_ht": 5,
    "c_pro_2t": 4,
    "c_sof_2t": 6,
    "c_pro_ft": 8,
    "c_sof_ft": 11,
    "gols_pro_ht": 1,
    "gols_sof_ht": 1,
    "gols_pro_ft": 2,
    "gols_sof_ft": 1,
    "posse": 46,
    "fin": 11
   }
  ]
 },
 "New York City": {
  "time": "New York City",
  "n_jogos_total": 6,
  "n_casa": 3,
  "n_fora": 3,
  "volume": {
   "casa_pro_ft": 5,
   "casa_sof_ft": 4,
   "casa_total_ft": 9,
   "fora_pro_ft": 2,
   "fora_sof_ft": 6.67,
   "fora_total_ft": 8.67
  },
  "pos_gol_pro": {
   "n": 2,
   "c_2t_pro": 2.5,
   "c_2t_sof": 3.5,
   "diff": -1.0,
   "estilo": "RECUA_POS_GOL"
  },
  "pos_gol_contra": {
   "n": 3,
   "c_2t_pro": 2.67,
   "c_2t_sof": 2.67,
   "diff": 0.0,
   "estilo": "EQUILIBRADO_REACAO"
  },
  "distribuicao_HT2T": {
   "pct_ht": 23.8,
   "categoria": "ASFIXIA_FINAL",
   "ht_pro_avg": 0.83,
   "t2_pro_avg": 2.67
  },
  "sangrador": {
   "sof_avg": 5.33,
   "posse_avg": 59,
   "tipo": "NORMAL"
  },
  "eficacia": {
   "cantos_por_gol": 3.5,
   "categoria": "NORMAL",
   "total_gols": 6,
   "total_cantos": 21
  },
  "regime_atual": {
   "status": "⚪ NEUTRO",
   "obs": "Sem direção clara | sd 1.7 | desvio +0.0",
   "ultimos_jogos": [
    6,
    3,
    2,
    3
   ]
  },
  "historico": [
   {
    "data": "18.04.2026 20:30",
    "rodada": "R7",
    "local": "CASA",
    "adv": "Charlotte",
    "c_pro_ht": 3,
    "c_sof_ht": 0,
    "c_pro_2t": 3,
    "c_sof_2t": 1,
    "c_pro_ft": 6,
    "c_sof_ft": 1,
    "gols_pro_ht": 0,
    "gols_sof_ht": 0,
    "gols_pro_ft": 1,
    "gols_sof_ft": 2,
    "posse": 64,
    "fin": 23
   },
   {
    "data": "25.04.2026 15:30",
    "rodada": "R8",
    "local": "FORA",
    "adv": "CF Montreal",
    "c_pro_ht": 0,
    "c_sof_ht": 0,
    "c_pro_2t": 1,
    "c_sof_2t": 3,
    "c_pro_ft": 1,
    "c_sof_ft": 3,
    "gols_pro_ht": 0,
    "gols_sof_ht": 1,
    "gols_pro_ft": 0,
    "gols_sof_ft": 1,
    "posse": 65,
    "fin": 4
   },
   {
    "data": "03.05.2026 16:00",
    "rodada": "R9",
    "local": "CASA",
    "adv": "DC United",
    "c_pro_ht": 2,
    "c_sof_ht": 2,
    "c_pro_2t": 4,
    "c_sof_2t": 1,
    "c_pro_ft": 6,
    "c_sof_ft": 3,
    "gols_pro_ht": 0,
    "gols_sof_ht": 1,
    "gols_pro_ft": 0,
    "gols_sof_ft": 2,
    "posse": 73,
    "fin": 9
   },
   {
    "data": "10.05.2026 17:30",
    "rodada": "R10",
    "local": "CASA",
    "adv": "Columbus Crew",
    "c_pro_ht": 0,
    "c_sof_ht": 4,
    "c_pro_2t": 3,
    "c_sof_2t": 4,
    "c_pro_ft": 3,
    "c_sof_ft": 8,
    "gols_pro_ht": 2,
    "gols_sof_ht": 0,
    "gols_pro_ft": 3,
    "gols_sof_ft": 0,
    "posse": 42,
    "fin": 9
   },
   {
    "data": "13.05.2026 20:15",
    "rodada": "R11",
    "local": "FORA",
    "adv": "Charlotte",
    "c_pro_ht": 0,
    "c_sof_ht": 5,
    "c_pro_2t": 2,
    "c_sof_2t": 3,
    "c_pro_ft": 2,
    "c_sof_ft": 8,
    "gols_pro_ht": 1,
    "gols_sof_ht": 0,
    "gols_pro_ft": 1,
    "gols_sof_ft": 0,
    "posse": 53,
    "fin": 4
   },
   {
    "data": "16.05.2026 20:30",
    "rodada": "R12",
    "local": "FORA",
    "adv": "New York Red Bulls",
    "c_pro_ht": 0,
    "c_sof_ht": 5,
    "c_pro_2t": 3,
    "c_sof_2t": 4,
    "c_pro_ft": 3,
    "c_sof_ft": 9,
    "gols_pro_ht": 0,
    "gols_sof_ht": 1,
    "gols_pro_ft": 1,
    "gols_sof_ft": 1,
    "posse": 57,
    "fin": 14
   }
  ]
 },
 "New York Red Bulls": {
  "time": "New York Red Bulls",
  "n_jogos_total": 6,
  "n_casa": 3,
  "n_fora": 3,
  "volume": {
   "casa_pro_ft": 6.67,
   "casa_sof_ft": 3,
   "casa_total_ft": 9.67,
   "fora_pro_ft": 5.67,
   "fora_sof_ft": 4,
   "fora_total_ft": 9.67
  },
  "pos_gol_pro": {
   "n": 3,
   "c_2t_pro": 3,
   "c_2t_sof": 3,
   "diff": 0,
   "estilo": "EQUILIBRADO_POS_GOL"
  },
  "pos_gol_contra": {
   "n": 2,
   "c_2t_pro": 4.5,
   "c_2t_sof": 1.5,
   "diff": 3.0,
   "estilo": "REAGE_PRESSIONA"
  },
  "distribuicao_HT2T": {
   "pct_ht": 43.2,
   "categoria": "DISTRIBUIDO",
   "ht_pro_avg": 2.67,
   "t2_pro_avg": 3.5
  },
  "sangrador": {
   "sof_avg": 3.5,
   "posse_avg": 48,
   "tipo": "DEFESA_SOLIDA"
  },
  "eficacia": {
   "cantos_por_gol": 4.63,
   "categoria": "NORMAL",
   "total_gols": 8,
   "total_cantos": 37
  },
  "regime_atual": {
   "status": "🔴 QUEBRADO",
   "obs": "Alta variância nos últimos jogos (sd 3.2) | sem padrão claro",
   "ultimos_jogos": [
    8,
    3,
    3,
    9
   ]
  },
  "historico": [
   {
    "data": "18.04.2026 15:30",
    "rodada": "R7",
    "local": "FORA",
    "adv": "CF Montreal",
    "c_pro_ht": 3,
    "c_sof_ht": 0,
    "c_pro_2t": 4,
    "c_sof_2t": 2,
    "c_pro_ft": 7,
    "c_sof_ft": 2,
    "gols_pro_ht": 0,
    "gols_sof_ht": 2,
    "gols_pro_ft": 1,
    "gols_sof_ft": 4,
    "posse": 68,
    "fin": 8
   },
   {
    "data": "25.04.2026 20:30",
    "rodada": "R8",
    "local": "FORA",
    "adv": "FC Cincinnati",
    "c_pro_ht": 2,
    "c_sof_ht": 3,
    "c_pro_2t": 5,
    "c_sof_2t": 1,
    "c_pro_ft": 7,
    "c_sof_ft": 4,
    "gols_pro_ht": 0,
    "gols_sof_ht": 2,
    "gols_pro_ft": 0,
    "gols_sof_ft": 2,
    "posse": 52,
    "fin": 19
   },
   {
    "data": "02.05.2026 20:30",
    "rodada": "R9",
    "local": "CASA",
    "adv": "FC Dallas",
    "c_pro_ht": 5,
    "c_sof_ht": 2,
    "c_pro_2t": 3,
    "c_sof_2t": 2,
    "c_pro_ft": 8,
    "c_sof_ft": 4,
    "gols_pro_ht": 0,
    "gols_sof_ht": 0,
    "gols_pro_ft": 0,
    "gols_sof_ft": 2,
    "posse": 58,
    "fin": 9
   },
   {
    "data": "09.05.2026 15:30",
    "rodada": "R10",
    "local": "FORA",
    "adv": "Chicago Fire",
    "c_pro_ht": 0,
    "c_sof_ht": 2,
    "c_pro_2t": 3,
    "c_sof_2t": 4,
    "c_pro_ft": 3,
    "c_sof_ft": 6,
    "gols_pro_ht": 1,
    "gols_sof_ht": 0,
    "gols_pro_ft": 3,
    "gols_sof_ft": 1,
    "posse": 36,
    "fin": 9
   },
   {
    "data": "13.05.2026 20:30",
    "rodada": "R11",
    "local": "CASA",
    "adv": "Columbus Crew",
    "c_pro_ht": 1,
    "c_sof_ht": 0,
    "c_pro_2t": 2,
    "c_sof_2t": 2,
    "c_pro_ft": 3,
    "c_sof_ft": 2,
    "gols_pro_ht": 2,
    "gols_sof_ht": 1,
    "gols_pro_ft": 3,
    "gols_sof_ft": 2,
    "posse": 31,
    "fin": 13
   },
   {
    "data": "16.05.2026 20:30",
    "rodada": "R12",
    "local": "CASA",
    "adv": "New York City",
    "c_pro_ht": 5,
    "c_sof_ht": 0,
    "c_pro_2t": 4,
    "c_sof_2t": 3,
    "c_pro_ft": 9,
    "c_sof_ft": 3,
    "gols_pro_ht": 1,
    "gols_sof_ht": 0,
    "gols_pro_ft": 1,
    "gols_sof_ft": 1,
    "posse": 43,
    "fin": 12
   }
  ]
 },
 "Orlando City": {
  "time": "Orlando City",
  "n_jogos_total": 7,
  "n_casa": 3,
  "n_fora": 4,
  "volume": {
   "casa_pro_ft": 3.33,
   "casa_sof_ft": 7.67,
   "casa_total_ft": 11.0,
   "fora_pro_ft": 3.5,
   "fora_sof_ft": 9,
   "fora_total_ft": 12.5
  },
  "pos_gol_pro": {
   "n": 3,
   "c_2t_pro": 1.67,
   "c_2t_sof": 2.33,
   "diff": -0.67,
   "estilo": "EQUILIBRADO_POS_GOL"
  },
  "pos_gol_contra": {
   "n": 2,
   "c_2t_pro": 2.5,
   "c_2t_sof": 3,
   "diff": -0.5,
   "estilo": "EQUILIBRADO_REACAO"
  },
  "distribuicao_HT2T": {
   "pct_ht": 45.8,
   "categoria": "DISTRIBUIDO",
   "ht_pro_avg": 1.57,
   "t2_pro_avg": 1.86
  },
  "sangrador": {
   "sof_avg": 8.43,
   "posse_avg": 48.4,
   "tipo": "SANGRA_SEM_BOLA"
  },
  "eficacia": {
   "cantos_por_gol": 2.0,
   "categoria": "CLINICA",
   "total_gols": 12,
   "total_cantos": 24
  },
  "regime_atual": {
   "status": "⚪ NEUTRO",
   "obs": "Sem direção clara | sd 1.0 | desvio -0.7",
   "ultimos_jogos": [
    2,
    3,
    2,
    4
   ]
  },
  "historico": [
   {
    "data": "12.04.2026 20:00",
    "rodada": "R7",
    "local": "FORA",
    "adv": "Columbus Crew",
    "c_pro_ht": 0,
    "c_sof_ht": 6,
    "c_pro_2t": 1,
    "c_sof_2t": 2,
    "c_pro_ft": 1,
    "c_sof_ft": 8,
    "gols_pro_ht": 1,
    "gols_sof_ht": 0,
    "gols_pro_ft": 1,
    "gols_sof_ft": 1,
    "posse": 35,
    "fin": 5
   },
   {
    "data": "18.04.2026 20:30",
    "rodada": "R7",
    "local": "CASA",
    "adv": "Houston Dynamo",
    "c_pro_ht": 3,
    "c_sof_ht": 3,
    "c_pro_2t": 1,
    "c_sof_2t": 0,
    "c_pro_ft": 4,
    "c_sof_ft": 3,
    "gols_pro_ht": 0,
    "gols_sof_ht": 0,
    "gols_pro_ft": 0,
    "gols_sof_ft": 1,
    "posse": 60,
    "fin": 17
   },
   {
    "data": "25.04.2026 20:30",
    "rodada": "R8",
    "local": "FORA",
    "adv": "DC United",
    "c_pro_ht": 5,
    "c_sof_ht": 3,
    "c_pro_2t": 3,
    "c_sof_2t": 4,
    "c_pro_ft": 8,
    "c_sof_ft": 7,
    "gols_pro_ht": 0,
    "gols_sof_ht": 1,
    "gols_pro_ft": 2,
    "gols_sof_ft": 3,
    "posse": 62,
    "fin": 8
   },
   {
    "data": "02.05.2026 20:15",
    "rodada": "R9",
    "local": "FORA",
    "adv": "Inter Miami",
    "c_pro_ht": 0,
    "c_sof_ht": 8,
    "c_pro_2t": 2,
    "c_sof_2t": 2,
    "c_pro_ft": 2,
    "c_sof_ft": 10,
    "gols_pro_ht": 1,
    "gols_sof_ht": 3,
    "gols_pro_ft": 4,
    "gols_sof_ft": 3,
    "posse": 36,
    "fin": 13
   },
   {
    "data": "09.05.2026 17:30",
    "rodada": "R10",
    "local": "FORA",
    "adv": "CF Montreal",
    "c_pro_ht": 1,
    "c_sof_ht": 4,
    "c_pro_2t": 2,
    "c_sof_2t": 7,
    "c_pro_ft": 3,
    "c_sof_ft": 11,
    "gols_pro_ht": 0,
    "gols_sof_ht": 0,
    "gols_pro_ft": 0,
    "gols_sof_ft": 2,
    "posse": 47,
    "fin": 8
   },
   {
    "data": "13.05.2026 20:30",
    "rodada": "R11",
    "local": "CASA",
    "adv": "Philadelphia Union",
    "c_pro_ht": 0,
    "c_sof_ht": 7,
    "c_pro_2t": 2,
    "c_sof_2t": 3,
    "c_pro_ft": 2,
    "c_sof_ft": 10,
    "gols_pro_ht": 2,
    "gols_sof_ht": 0,
    "gols_pro_ft": 4,
    "gols_sof_ft": 3,
    "posse": 54,
    "fin": 12
   },
   {
    "data": "16.05.2026 20:30",
    "rodada": "R12",
    "local": "CASA",
    "adv": "Atlanta Utd",
    "c_pro_ht": 2,
    "c_sof_ht": 8,
    "c_pro_2t": 2,
    "c_sof_2t": 2,
    "c_pro_ft": 4,
    "c_sof_ft": 10,
    "gols_pro_ht": 1,
    "gols_sof_ht": 0,
    "gols_pro_ft": 1,
    "gols_sof_ft": 1,
    "posse": 45,
    "fin": 7
   }
  ]
 },
 "Philadelphia Union": {
  "time": "Philadelphia Union",
  "n_jogos_total": 6,
  "n_casa": 3,
  "n_fora": 3,
  "volume": {
   "casa_pro_ft": 7.33,
   "casa_sof_ft": 2.33,
   "casa_total_ft": 9.67,
   "fora_pro_ft": 5.67,
   "fora_sof_ft": 4.33,
   "fora_total_ft": 10.0
  },
  "pos_gol_pro": null,
  "pos_gol_contra": {
   "n": 3,
   "c_2t_pro": 2.33,
   "c_2t_sof": 1.33,
   "diff": 1.0,
   "estilo": "REAGE_PRESSIONA"
  },
  "distribuicao_HT2T": {
   "pct_ht": 51.3,
   "categoria": "DISTRIBUIDO",
   "ht_pro_avg": 3.33,
   "t2_pro_avg": 3.17
  },
  "sangrador": {
   "sof_avg": 3.33,
   "posse_avg": 45.8,
   "tipo": "DEFESA_SOLIDA"
  },
  "eficacia": {
   "cantos_por_gol": 7.8,
   "categoria": "ESTERIL",
   "total_gols": 5,
   "total_cantos": 39
  },
  "regime_atual": {
   "status": "🔴 QUEBRADO",
   "obs": "Alta variância nos últimos jogos (sd 3.1) | sem padrão claro",
   "ultimos_jogos": [
    5,
    3,
    10,
    4
   ]
  },
  "historico": [
   {
    "data": "18.04.2026 20:30",
    "rodada": "R7",
    "local": "CASA",
    "adv": "DC United",
    "c_pro_ht": 4,
    "c_sof_ht": 1,
    "c_pro_2t": 9,
    "c_sof_2t": 0,
    "c_pro_ft": 13,
    "c_sof_ft": 1,
    "gols_pro_ht": 0,
    "gols_sof_ht": 0,
    "gols_pro_ft": 0,
    "gols_sof_ft": 0,
    "posse": 62,
    "fin": 17
   },
   {
    "data": "25.04.2026 20:30",
    "rodada": "R8",
    "local": "FORA",
    "adv": "Columbus Crew",
    "c_pro_ht": 2,
    "c_sof_ht": 2,
    "c_pro_2t": 2,
    "c_sof_2t": 0,
    "c_pro_ft": 4,
    "c_sof_ft": 2,
    "gols_pro_ht": 0,
    "gols_sof_ht": 2,
    "gols_pro_ft": 0,
    "gols_sof_ft": 2,
    "posse": 44,
    "fin": 10
   },
   {
    "data": "02.05.2026 20:30",
    "rodada": "R9",
    "local": "CASA",
    "adv": "Nashville SC",
    "c_pro_ht": 2,
    "c_sof_ht": 0,
    "c_pro_2t": 3,
    "c_sof_2t": 2,
    "c_pro_ft": 5,
    "c_sof_ft": 2,
    "gols_pro_ht": 0,
    "gols_sof_ht": 0,
    "gols_pro_ft": 0,
    "gols_sof_ft": 0,
    "posse": 46,
    "fin": 16
   },
   {
    "data": "09.05.2026 20:30",
    "rodada": "R10",
    "local": "FORA",
    "adv": "New England Revolution",
    "c_pro_ht": 3,
    "c_sof_ht": 5,
    "c_pro_2t": 0,
    "c_sof_2t": 4,
    "c_pro_ft": 3,
    "c_sof_ft": 9,
    "gols_pro_ht": 1,
    "gols_sof_ht": 0,
    "gols_pro_ft": 1,
    "gols_sof_ft": 2,
    "posse": 39,
    "fin": 11
   },
   {
    "data": "13.05.2026 20:30",
    "rodada": "R11",
    "local": "FORA",
    "adv": "Orlando City",
    "c_pro_ht": 7,
    "c_sof_ht": 0,
    "c_pro_2t": 3,
    "c_sof_2t": 2,
    "c_pro_ft": 10,
    "c_sof_ft": 2,
    "gols_pro_ht": 0,
    "gols_sof_ht": 2,
    "gols_pro_ft": 3,
    "gols_sof_ft": 4,
    "posse": 46,
    "fin": 26
   },
   {
    "data": "16.05.2026 20:30",
    "rodada": "R12",
    "local": "CASA",
    "adv": "Columbus Crew",
    "c_pro_ht": 2,
    "c_sof_ht": 2,
    "c_pro_2t": 2,
    "c_sof_2t": 2,
    "c_pro_ft": 4,
    "c_sof_ft": 4,
    "gols_pro_ht": 0,
    "gols_sof_ht": 1,
    "gols_pro_ft": 1,
    "gols_sof_ft": 1,
    "posse": 38,
    "fin": 12
   }
  ]
 },
 "Portland Timbers": {
  "time": "Portland Timbers",
  "n_jogos_total": 5,
  "n_casa": 1,
  "n_fora": 4,
  "volume": {
   "casa_pro_ft": 4,
   "casa_sof_ft": 4,
   "casa_total_ft": 8,
   "fora_pro_ft": 5.25,
   "fora_sof_ft": 5.25,
   "fora_total_ft": 10.5
  },
  "pos_gol_pro": null,
  "pos_gol_contra": {
   "n": 3,
   "c_2t_pro": 2,
   "c_2t_sof": 3.33,
   "diff": -1.33,
   "estilo": "DESISTE_RECUA"
  },
  "distribuicao_HT2T": {
   "pct_ht": 48.0,
   "categoria": "DISTRIBUIDO",
   "ht_pro_avg": 2.4,
   "t2_pro_avg": 2.6
  },
  "sangrador": {
   "sof_avg": 5,
   "posse_avg": 51.2,
   "tipo": "NORMAL"
  },
  "eficacia": {
   "cantos_por_gol": 2.5,
   "categoria": "CLINICA",
   "total_gols": 10,
   "total_cantos": 25
  },
  "regime_atual": {
   "status": "⚪ NEUTRO",
   "obs": "Sem direção clara | sd 3.0 | desvio +0.2",
   "ultimos_jogos": [
    6,
    2,
    4,
    9
   ]
  },
  "historico": [
   {
    "data": "18.04.2026 21:30",
    "rodada": "R7",
    "local": "FORA",
    "adv": "Minnesota United",
    "c_pro_ht": 2,
    "c_sof_ht": 1,
    "c_pro_2t": 2,
    "c_sof_2t": 2,
    "c_pro_ft": 4,
    "c_sof_ft": 3,
    "gols_pro_ht": 0,
    "gols_sof_ht": 1,
    "gols_pro_ft": 0,
    "gols_sof_ft": 2,
    "posse": 56,
    "fin": 13
   },
   {
    "data": "25.04.2026 22:30",
    "rodada": "R8",
    "local": "FORA",
    "adv": "San Diego FC",
    "c_pro_ht": 1,
    "c_sof_ht": 5,
    "c_pro_2t": 5,
    "c_sof_2t": 1,
    "c_pro_ft": 6,
    "c_sof_ft": 6,
    "gols_pro_ht": 1,
    "gols_sof_ht": 1,
    "gols_pro_ft": 2,
    "gols_sof_ft": 1,
    "posse": 33,
    "fin": 11
   },
   {
    "data": "02.05.2026 17:45",
    "rodada": "R9",
    "local": "FORA",
    "adv": "Real Salt Lake",
    "c_pro_ht": 2,
    "c_sof_ht": 3,
    "c_pro_2t": 0,
    "c_sof_2t": 3,
    "c_pro_ft": 2,
    "c_sof_ft": 6,
    "gols_pro_ht": 0,
    "gols_sof_ht": 2,
    "gols_pro_ft": 0,
    "gols_sof_ft": 2,
    "posse": 47,
    "fin": 11
   },
   {
    "data": "09.05.2026 23:30",
    "rodada": "R10",
    "local": "CASA",
    "adv": "Sporting Kansas City",
    "c_pro_ht": 2,
    "c_sof_ht": 0,
    "c_pro_2t": 2,
    "c_sof_2t": 4,
    "c_pro_ft": 4,
    "c_sof_ft": 4,
    "gols_pro_ht": 4,
    "gols_sof_ht": 0,
    "gols_pro_ft": 6,
    "gols_sof_ft": 0,
    "posse": 63,
    "fin": 16
   },
   {
    "data": "13.05.2026 20:30",
    "rodada": "R11",
    "local": "FORA",
    "adv": "CF Montreal",
    "c_pro_ht": 5,
    "c_sof_ht": 1,
    "c_pro_2t": 4,
    "c_sof_2t": 5,
    "c_pro_ft": 9,
    "c_sof_ft": 6,
    "gols_pro_ht": 1,
    "gols_sof_ht": 2,
    "gols_pro_ft": 2,
    "gols_sof_ft": 2,
    "posse": 57,
    "fin": 14
   }
  ]
 },
 "Real Salt Lake": {
  "time": "Real Salt Lake",
  "n_jogos_total": 6,
  "n_casa": 4,
  "n_fora": 2,
  "volume": {
   "casa_pro_ft": 3.25,
   "casa_sof_ft": 4.25,
   "casa_total_ft": 7.5,
   "fora_pro_ft": 3.5,
   "fora_sof_ft": 5.5,
   "fora_total_ft": 9.0
  },
  "pos_gol_pro": {
   "n": 2,
   "c_2t_pro": 1.5,
   "c_2t_sof": 3.5,
   "diff": -2.0,
   "estilo": "RECUA_POS_GOL"
  },
  "pos_gol_contra": null,
  "distribuicao_HT2T": {
   "pct_ht": 60.0,
   "categoria": "BLITZ_INICIAL",
   "ht_pro_avg": 2,
   "t2_pro_avg": 1.33
  },
  "sangrador": {
   "sof_avg": 4.67,
   "posse_avg": 56,
   "tipo": "NORMAL"
  },
  "eficacia": {
   "cantos_por_gol": 1.54,
   "categoria": "CLINICA",
   "total_gols": 13,
   "total_cantos": 20
  },
  "regime_atual": {
   "status": "🟡 EMERGENTE",
   "obs": "Tendência emergente em alta | sd 2.2 | desvio +1.4",
   "ultimos_jogos": [
    6,
    7,
    4,
    2
   ]
  },
  "historico": [
   {
    "data": "18.04.2026 22:30",
    "rodada": "R7",
    "local": "CASA",
    "adv": "San Diego FC",
    "c_pro_ht": 1,
    "c_sof_ht": 1,
    "c_pro_2t": 0,
    "c_sof_2t": 7,
    "c_pro_ft": 1,
    "c_sof_ft": 8,
    "gols_pro_ht": 4,
    "gols_sof_ht": 1,
    "gols_pro_ft": 4,
    "gols_sof_ft": 2,
    "posse": 48,
    "fin": 16
   },
   {
    "data": "26.04.2026 20:00",
    "rodada": "R8",
    "local": "FORA",
    "adv": "Los Angeles Galaxy",
    "c_pro_ht": 0,
    "c_sof_ht": 5,
    "c_pro_2t": 0,
    "c_sof_2t": 2,
    "c_pro_ft": 0,
    "c_sof_ft": 7,
    "gols_pro_ht": 1,
    "gols_sof_ht": 1,
    "gols_pro_ft": 1,
    "gols_sof_ft": 2,
    "posse": 61,
    "fin": 15
   },
   {
    "data": "02.05.2026 17:45",
    "rodada": "R9",
    "local": "CASA",
    "adv": "Portland Timbers",
    "c_pro_ht": 3,
    "c_sof_ht": 2,
    "c_pro_2t": 3,
    "c_sof_2t": 0,
    "c_pro_ft": 6,
    "c_sof_ft": 2,
    "gols_pro_ht": 2,
    "gols_sof_ht": 0,
    "gols_pro_ft": 2,
    "gols_sof_ft": 0,
    "posse": 53,
    "fin": 25
   },
   {
    "data": "09.05.2026 21:30",
    "rodada": "R10",
    "local": "FORA",
    "adv": "FC Dallas",
    "c_pro_ht": 5,
    "c_sof_ht": 2,
    "c_pro_2t": 2,
    "c_sof_2t": 2,
    "c_pro_ft": 7,
    "c_sof_ft": 4,
    "gols_pro_ht": 0,
    "gols_sof_ht": 2,
    "gols_pro_ft": 1,
    "gols_sof_ft": 3,
    "posse": 73,
    "fin": 9
   },
   {
    "data": "13.05.2026 22:30",
    "rodada": "R11",
    "local": "CASA",
    "adv": "Houston Dynamo",
    "c_pro_ht": 2,
    "c_sof_ht": 1,
    "c_pro_2t": 2,
    "c_sof_2t": 0,
    "c_pro_ft": 4,
    "c_sof_ft": 1,
    "gols_pro_ht": 0,
    "gols_sof_ht": 0,
    "gols_pro_ft": 3,
    "gols_sof_ft": 0,
    "posse": 53,
    "fin": 9
   },
   {
    "data": "16.05.2026 22:30",
    "rodada": "R12",
    "local": "CASA",
    "adv": "Colorado Rapids",
    "c_pro_ht": 1,
    "c_sof_ht": 3,
    "c_pro_2t": 1,
    "c_sof_2t": 3,
    "c_pro_ft": 2,
    "c_sof_ft": 6,
    "gols_pro_ht": 1,
    "gols_sof_ht": 1,
    "gols_pro_ft": 2,
    "gols_sof_ft": 1,
    "posse": 48,
    "fin": 17
   }
  ]
 },
 "San Diego FC": {
  "time": "San Diego FC",
  "n_jogos_total": 7,
  "n_casa": 5,
  "n_fora": 2,
  "volume": {
   "casa_pro_ft": 5,
   "casa_sof_ft": 4,
   "casa_total_ft": 9,
   "fora_pro_ft": 5,
   "fora_sof_ft": 4.5,
   "fora_total_ft": 9.5
  },
  "pos_gol_pro": {
   "n": 3,
   "c_2t_pro": 1.33,
   "c_2t_sof": 3.67,
   "diff": -2.33,
   "estilo": "RECUA_POS_GOL"
  },
  "pos_gol_contra": {
   "n": 2,
   "c_2t_pro": 5,
   "c_2t_sof": 2.5,
   "diff": 2.5,
   "estilo": "REAGE_PRESSIONA"
  },
  "distribuicao_HT2T": {
   "pct_ht": 45.7,
   "categoria": "DISTRIBUIDO",
   "ht_pro_avg": 2.29,
   "t2_pro_avg": 2.71
  },
  "sangrador": {
   "sof_avg": 4.14,
   "posse_avg": 59.1,
   "tipo": "NORMAL"
  },
  "eficacia": {
   "cantos_por_gol": 2.33,
   "categoria": "CLINICA",
   "total_gols": 15,
   "total_cantos": 35
  },
  "regime_atual": {
   "status": "⚪ NEUTRO",
   "obs": "Sem direção clara | sd 2.6 | desvio -0.8",
   "ultimos_jogos": [
    2,
    2,
    6,
    7
   ]
  },
  "historico": [
   {
    "data": "11.04.2026 23:30",
    "rodada": "R7",
    "local": "CASA",
    "adv": "Minnesota United",
    "c_pro_ht": 1,
    "c_sof_ht": 0,
    "c_pro_2t": 3,
    "c_sof_2t": 5,
    "c_pro_ft": 4,
    "c_sof_ft": 5,
    "gols_pro_ht": 1,
    "gols_sof_ht": 2,
    "gols_pro_ft": 1,
    "gols_sof_ft": 2,
    "posse": 64,
    "fin": 17
   },
   {
    "data": "18.04.2026 22:30",
    "rodada": "R7",
    "local": "FORA",
    "adv": "Real Salt Lake",
    "c_pro_ht": 1,
    "c_sof_ht": 1,
    "c_pro_2t": 7,
    "c_sof_2t": 0,
    "c_pro_ft": 8,
    "c_sof_ft": 1,
    "gols_pro_ht": 1,
    "gols_sof_ht": 4,
    "gols_pro_ft": 2,
    "gols_sof_ft": 4,
    "posse": 52,
    "fin": 9
   },
   {
    "data": "25.04.2026 22:30",
    "rodada": "R8",
    "local": "CASA",
    "adv": "Portland Timbers",
    "c_pro_ht": 5,
    "c_sof_ht": 1,
    "c_pro_2t": 1,
    "c_sof_2t": 5,
    "c_pro_ft": 6,
    "c_sof_ft": 6,
    "gols_pro_ht": 1,
    "gols_sof_ht": 1,
    "gols_pro_ft": 1,
    "gols_sof_ft": 2,
    "posse": 67,
    "fin": 10
   },
   {
    "data": "02.05.2026 22:30",
    "rodada": "R9",
    "local": "CASA",
    "adv": "Los Angeles FC",
    "c_pro_ht": 2,
    "c_sof_ht": 0,
    "c_pro_2t": 0,
    "c_sof_2t": 3,
    "c_pro_ft": 2,
    "c_sof_ft": 3,
    "gols_pro_ht": 1,
    "gols_sof_ht": 0,
    "gols_pro_ft": 2,
    "gols_sof_ft": 2,
    "posse": 56,
    "fin": 8
   },
   {
    "data": "09.05.2026 23:30",
    "rodada": "R10",
    "local": "FORA",
    "adv": "Seattle Sounders",
    "c_pro_ht": 1,
    "c_sof_ht": 2,
    "c_pro_2t": 1,
    "c_sof_2t": 6,
    "c_pro_ft": 2,
    "c_sof_ft": 8,
    "gols_pro_ht": 1,
    "gols_sof_ht": 0,
    "gols_pro_ft": 1,
    "gols_sof_ft": 1,
    "posse": 53,
    "fin": 15
   },
   {
    "data": "13.05.2026 22:30",
    "rodada": "R11",
    "local": "CASA",
    "adv": "Austin FC",
    "c_pro_ht": 3,
    "c_sof_ht": 2,
    "c_pro_2t": 3,
    "c_sof_2t": 2,
    "c_pro_ft": 6,
    "c_sof_ft": 4,
    "gols_pro_ht": 2,
    "gols_sof_ht": 0,
    "gols_pro_ft": 5,
    "gols_sof_ft": 0,
    "posse": 59,
    "fin": 22
   },
   {
    "data": "16.05.2026 22:30",
    "rodada": "R12",
    "local": "CASA",
    "adv": "FC Cincinnati",
    "c_pro_ht": 3,
    "c_sof_ht": 1,
    "c_pro_2t": 4,
    "c_sof_2t": 1,
    "c_pro_ft": 7,
    "c_sof_ft": 2,
    "gols_pro_ht": 1,
    "gols_sof_ht": 1,
    "gols_pro_ft": 3,
    "gols_sof_ft": 3,
    "posse": 63,
    "fin": 16
   }
  ]
 },
 "San Jose Earthquakes": {
  "time": "San Jose Earthquakes",
  "n_jogos_total": 7,
  "n_casa": 3,
  "n_fora": 4,
  "volume": {
   "casa_pro_ft": 9,
   "casa_sof_ft": 3,
   "casa_total_ft": 12,
   "fora_pro_ft": 5.25,
   "fora_sof_ft": 8,
   "fora_total_ft": 13.25
  },
  "pos_gol_pro": {
   "n": 2,
   "c_2t_pro": 0.5,
   "c_2t_sof": 3,
   "diff": -2.5,
   "estilo": "RECUA_POS_GOL"
  },
  "pos_gol_contra": null,
  "distribuicao_HT2T": {
   "pct_ht": 37.5,
   "categoria": "DISTRIBUIDO",
   "ht_pro_avg": 2.57,
   "t2_pro_avg": 4.29
  },
  "sangrador": {
   "sof_avg": 5.86,
   "posse_avg": 47.3,
   "tipo": "NORMAL"
  },
  "eficacia": {
   "cantos_por_gol": 2.67,
   "categoria": "CLINICA",
   "total_gols": 18,
   "total_cantos": 48
  },
  "regime_atual": {
   "status": "🔴 QUEBRADO",
   "obs": "Alta variância nos últimos jogos (sd 4.3) | sem padrão claro",
   "ultimos_jogos": [
    9,
    2,
    6,
    12
   ]
  },
  "historico": [
   {
    "data": "19.04.2026 20:00",
    "rodada": "R7",
    "local": "FORA",
    "adv": "Los Angeles FC",
    "c_pro_ht": 1,
    "c_sof_ht": 1,
    "c_pro_2t": 2,
    "c_sof_2t": 4,
    "c_pro_ft": 3,
    "c_sof_ft": 5,
    "gols_pro_ht": 0,
    "gols_sof_ht": 0,
    "gols_pro_ft": 4,
    "gols_sof_ft": 1,
    "posse": 47,
    "fin": 12
   },
   {
    "data": "22.04.2026 23:30",
    "rodada": "R8",
    "local": "CASA",
    "adv": "Austin FC",
    "c_pro_ht": 6,
    "c_sof_ht": 1,
    "c_pro_2t": 7,
    "c_sof_2t": 0,
    "c_pro_ft": 13,
    "c_sof_ft": 1,
    "gols_pro_ht": 0,
    "gols_sof_ht": 1,
    "gols_pro_ft": 5,
    "gols_sof_ft": 1,
    "posse": 69,
    "fin": 37
   },
   {
    "data": "25.04.2026 21:30",
    "rodada": "R8",
    "local": "FORA",
    "adv": "St. Louis City",
    "c_pro_ht": 2,
    "c_sof_ht": 5,
    "c_pro_2t": 1,
    "c_sof_2t": 5,
    "c_pro_ft": 3,
    "c_sof_ft": 10,
    "gols_pro_ht": 1,
    "gols_sof_ht": 0,
    "gols_pro_ft": 3,
    "gols_sof_ft": 2,
    "posse": 42,
    "fin": 9
   },
   {
    "data": "02.05.2026 14:00",
    "rodada": "R9",
    "local": "FORA",
    "adv": "Toronto FC",
    "c_pro_ht": 3,
    "c_sof_ht": 3,
    "c_pro_2t": 6,
    "c_sof_2t": 5,
    "c_pro_ft": 9,
    "c_sof_ft": 8,
    "gols_pro_ht": 1,
    "gols_sof_ht": 1,
    "gols_pro_ft": 1,
    "gols_sof_ft": 1,
    "posse": 52,
    "fin": 10
   },
   {
    "data": "09.05.2026 23:30",
    "rodada": "R10",
    "local": "CASA",
    "adv": "Vancouver Whitecaps",
    "c_pro_ht": 2,
    "c_sof_ht": 3,
    "c_pro_2t": 0,
    "c_sof_2t": 1,
    "c_pro_ft": 2,
    "c_sof_ft": 4,
    "gols_pro_ht": 1,
    "gols_sof_ht": 0,
    "gols_pro_ft": 1,
    "gols_sof_ft": 1,
    "posse": 29,
    "fin": 7
   },
   {
    "data": "13.05.2026 22:30",
    "rodada": "R11",
    "local": "FORA",
    "adv": "Seattle Sounders",
    "c_pro_ht": 2,
    "c_sof_ht": 7,
    "c_pro_2t": 4,
    "c_sof_2t": 2,
    "c_pro_ft": 6,
    "c_sof_ft": 9,
    "gols_pro_ht": 1,
    "gols_sof_ht": 1,
    "gols_pro_ft": 2,
    "gols_sof_ft": 3,
    "posse": 37,
    "fin": 11
   },
   {
    "data": "16.05.2026 23:30",
    "rodada": "R12",
    "local": "CASA",
    "adv": "FC Dallas",
    "c_pro_ht": 2,
    "c_sof_ht": 3,
    "c_pro_2t": 10,
    "c_sof_2t": 1,
    "c_pro_ft": 12,
    "c_sof_ft": 4,
    "gols_pro_ht": 1,
    "gols_sof_ht": 1,
    "gols_pro_ft": 2,
    "gols_sof_ft": 3,
    "posse": 55,
    "fin": 16
   }
  ]
 },
 "Seattle Sounders": {
  "time": "Seattle Sounders",
  "n_jogos_total": 6,
  "n_casa": 5,
  "n_fora": 1,
  "volume": {
   "casa_pro_ft": 6.2,
   "casa_sof_ft": 4.8,
   "casa_total_ft": 11.0,
   "fora_pro_ft": 9,
   "fora_sof_ft": 4,
   "fora_total_ft": 13
  },
  "pos_gol_pro": {
   "n": 2,
   "c_2t_pro": 1.5,
   "c_2t_sof": 4.5,
   "diff": -3.0,
   "estilo": "RECUA_POS_GOL"
  },
  "pos_gol_contra": {
   "n": 2,
   "c_2t_pro": 5.5,
   "c_2t_sof": 0.5,
   "diff": 5.0,
   "estilo": "REAGE_PRESSIONA"
  },
  "distribuicao_HT2T": {
   "pct_ht": 42.5,
   "categoria": "DISTRIBUIDO",
   "ht_pro_avg": 2.83,
   "t2_pro_avg": 3.83
  },
  "sangrador": {
   "sof_avg": 4.67,
   "posse_avg": 56.8,
   "tipo": "NORMAL"
  },
  "eficacia": {
   "cantos_por_gol": 3.64,
   "categoria": "NORMAL",
   "total_gols": 11,
   "total_cantos": 40
  },
  "regime_atual": {
   "status": "🟡 EMERGENTE",
   "obs": "Tendência emergente em alta | sd 1.9 | desvio +1.1",
   "ultimos_jogos": [
    9,
    8,
    9,
    5
   ]
  },
  "historico": [
   {
    "data": "18.04.2026 22:30",
    "rodada": "R7",
    "local": "CASA",
    "adv": "St. Louis City",
    "c_pro_ht": 4,
    "c_sof_ht": 3,
    "c_pro_2t": 1,
    "c_sof_2t": 5,
    "c_pro_ft": 5,
    "c_sof_ft": 8,
    "gols_pro_ht": 2,
    "gols_sof_ht": 0,
    "gols_pro_ft": 4,
    "gols_sof_ft": 1,
    "posse": 50,
    "fin": 13
   },
   {
    "data": "25.04.2026 23:30",
    "rodada": "R8",
    "local": "CASA",
    "adv": "FC Dallas",
    "c_pro_ht": 2,
    "c_sof_ht": 3,
    "c_pro_2t": 2,
    "c_sof_2t": 4,
    "c_pro_ft": 4,
    "c_sof_ft": 7,
    "gols_pro_ht": 2,
    "gols_sof_ht": 1,
    "gols_pro_ft": 2,
    "gols_sof_ft": 1,
    "posse": 58,
    "fin": 9
   },
   {
    "data": "02.05.2026 15:30",
    "rodada": "R9",
    "local": "FORA",
    "adv": "Sporting Kansas City",
    "c_pro_ht": 2,
    "c_sof_ht": 1,
    "c_pro_2t": 7,
    "c_sof_2t": 3,
    "c_pro_ft": 9,
    "c_sof_ft": 4,
    "gols_pro_ht": 1,
    "gols_sof_ht": 1,
    "gols_pro_ft": 1,
    "gols_sof_ft": 1,
    "posse": 65,
    "fin": 26
   },
   {
    "data": "09.05.2026 23:30",
    "rodada": "R10",
    "local": "CASA",
    "adv": "San Diego FC",
    "c_pro_ht": 2,
    "c_sof_ht": 1,
    "c_pro_2t": 6,
    "c_sof_2t": 1,
    "c_pro_ft": 8,
    "c_sof_ft": 2,
    "gols_pro_ht": 0,
    "gols_sof_ht": 1,
    "gols_pro_ft": 1,
    "gols_sof_ft": 1,
    "posse": 47,
    "fin": 26
   },
   {
    "data": "13.05.2026 22:30",
    "rodada": "R11",
    "local": "CASA",
    "adv": "San Jose Earthquakes",
    "c_pro_ht": 7,
    "c_sof_ht": 2,
    "c_pro_2t": 2,
    "c_sof_2t": 4,
    "c_pro_ft": 9,
    "c_sof_ft": 6,
    "gols_pro_ht": 1,
    "gols_sof_ht": 1,
    "gols_pro_ft": 3,
    "gols_sof_ft": 2,
    "posse": 63,
    "fin": 23
   },
   {
    "data": "16.05.2026 22:15",
    "rodada": "R12",
    "local": "CASA",
    "adv": "Los Angeles Galaxy",
    "c_pro_ht": 0,
    "c_sof_ht": 1,
    "c_pro_2t": 5,
    "c_sof_2t": 0,
    "c_pro_ft": 5,
    "c_sof_ft": 1,
    "gols_pro_ht": 0,
    "gols_sof_ht": 1,
    "gols_pro_ft": 0,
    "gols_sof_ft": 2,
    "posse": 58,
    "fin": 15
   }
  ]
 },
 "Sporting Kansas City": {
  "time": "Sporting Kansas City",
  "n_jogos_total": 6,
  "n_casa": 2,
  "n_fora": 4,
  "volume": {
   "casa_pro_ft": 4,
   "casa_sof_ft": 8.5,
   "casa_total_ft": 12.5,
   "fora_pro_ft": 4,
   "fora_sof_ft": 4.25,
   "fora_total_ft": 8.25
  },
  "pos_gol_pro": null,
  "pos_gol_contra": {
   "n": 3,
   "c_2t_pro": 3,
   "c_2t_sof": 1.67,
   "diff": 1.33,
   "estilo": "REAGE_PRESSIONA"
  },
  "distribuicao_HT2T": {
   "pct_ht": 37.5,
   "categoria": "DISTRIBUIDO",
   "ht_pro_avg": 1.5,
   "t2_pro_avg": 2.5
  },
  "sangrador": {
   "sof_avg": 5.67,
   "posse_avg": 40.8,
   "tipo": "NORMAL"
  },
  "eficacia": {
   "cantos_por_gol": 4.0,
   "categoria": "NORMAL",
   "total_gols": 6,
   "total_cantos": 24
  },
  "regime_atual": {
   "status": "⚪ NEUTRO",
   "obs": "Sem direção clara | sd 1.5 | desvio +0.8",
   "ultimos_jogos": [
    4,
    4,
    4,
    7
   ]
  },
  "historico": [
   {
    "data": "17.04.2026 23:30",
    "rodada": "R7",
    "local": "FORA",
    "adv": "Vancouver Whitecaps",
    "c_pro_ht": 0,
    "c_sof_ht": 5,
    "c_pro_2t": 3,
    "c_sof_2t": 1,
    "c_pro_ft": 3,
    "c_sof_ft": 6,
    "gols_pro_ht": 0,
    "gols_sof_ht": 3,
    "gols_pro_ft": 0,
    "gols_sof_ft": 3,
    "posse": 50,
    "fin": 3
   },
   {
    "data": "25.04.2026 21:30",
    "rodada": "R8",
    "local": "FORA",
    "adv": "Chicago Fire",
    "c_pro_ht": 0,
    "c_sof_ht": 1,
    "c_pro_2t": 2,
    "c_sof_2t": 3,
    "c_pro_ft": 2,
    "c_sof_ft": 4,
    "gols_pro_ht": 0,
    "gols_sof_ht": 0,
    "gols_pro_ft": 0,
    "gols_sof_ft": 5,
    "posse": 29,
    "fin": 6
   },
   {
    "data": "02.05.2026 15:30",
    "rodada": "R9",
    "local": "CASA",
    "adv": "Seattle Sounders",
    "c_pro_ht": 1,
    "c_sof_ht": 2,
    "c_pro_2t": 3,
    "c_sof_2t": 7,
    "c_pro_ft": 4,
    "c_sof_ft": 9,
    "gols_pro_ht": 1,
    "gols_sof_ht": 1,
    "gols_pro_ft": 1,
    "gols_sof_ft": 1,
    "posse": 35,
    "fin": 10
   },
   {
    "data": "09.05.2026 23:30",
    "rodada": "R10",
    "local": "FORA",
    "adv": "Portland Timbers",
    "c_pro_ht": 0,
    "c_sof_ht": 2,
    "c_pro_2t": 4,
    "c_sof_2t": 2,
    "c_pro_ft": 4,
    "c_sof_ft": 4,
    "gols_pro_ht": 0,
    "gols_sof_ht": 4,
    "gols_pro_ft": 0,
    "gols_sof_ft": 6,
    "posse": 37,
    "fin": 11
   },
   {
    "data": "13.05.2026 21:30",
    "rodada": "R11",
    "local": "CASA",
    "adv": "Los Angeles Galaxy",
    "c_pro_ht": 3,
    "c_sof_ht": 6,
    "c_pro_2t": 1,
    "c_sof_2t": 2,
    "c_pro_ft": 4,
    "c_sof_ft": 8,
    "gols_pro_ht": 2,
    "gols_sof_ht": 0,
    "gols_pro_ft": 3,
    "gols_sof_ft": 1,
    "posse": 40,
    "fin": 15
   },
   {
    "data": "16.05.2026 21:30",
    "rodada": "R12",
    "local": "FORA",
    "adv": "Austin FC",
    "c_pro_ht": 5,
    "c_sof_ht": 1,
    "c_pro_2t": 2,
    "c_sof_2t": 2,
    "c_pro_ft": 7,
    "c_sof_ft": 3,
    "gols_pro_ht": 0,
    "gols_sof_ht": 1,
    "gols_pro_ft": 2,
    "gols_sof_ft": 1,
    "posse": 54,
    "fin": 20
   }
  ]
 },
 "St. Louis City": {
  "time": "St. Louis City",
  "n_jogos_total": 6,
  "n_casa": 2,
  "n_fora": 4,
  "volume": {
   "casa_pro_ft": 6,
   "casa_sof_ft": 5.5,
   "casa_total_ft": 11.5,
   "fora_pro_ft": 5.75,
   "fora_sof_ft": 6.25,
   "fora_total_ft": 12.0
  },
  "pos_gol_pro": {
   "n": 2,
   "c_2t_pro": 0.5,
   "c_2t_sof": 5.5,
   "diff": -5.0,
   "estilo": "RECUA_POS_GOL"
  },
  "pos_gol_contra": {
   "n": 2,
   "c_2t_pro": 5,
   "c_2t_sof": 1,
   "diff": 4,
   "estilo": "REAGE_PRESSIONA"
  },
  "distribuicao_HT2T": {
   "pct_ht": 62.9,
   "categoria": "BLITZ_INICIAL",
   "ht_pro_avg": 3.67,
   "t2_pro_avg": 2.17
  },
  "sangrador": {
   "sof_avg": 6,
   "posse_avg": 48.7,
   "tipo": "SANGRA_SEM_BOLA"
  },
  "eficacia": {
   "cantos_por_gol": 5.0,
   "categoria": "NORMAL",
   "total_gols": 7,
   "total_cantos": 35
  },
  "regime_atual": {
   "status": "🔴 QUEBRADO",
   "obs": "Alta variância nos últimos jogos (sd 3.3) | sem padrão claro",
   "ultimos_jogos": [
    6,
    1,
    2,
    8
   ]
  },
  "historico": [
   {
    "data": "18.04.2026 22:30",
    "rodada": "R7",
    "local": "FORA",
    "adv": "Seattle Sounders",
    "c_pro_ht": 3,
    "c_sof_ht": 4,
    "c_pro_2t": 5,
    "c_sof_2t": 1,
    "c_pro_ft": 8,
    "c_sof_ft": 5,
    "gols_pro_ht": 0,
    "gols_sof_ht": 2,
    "gols_pro_ft": 1,
    "gols_sof_ft": 4,
    "posse": 50,
    "fin": 12
   },
   {
    "data": "25.04.2026 21:30",
    "rodada": "R8",
    "local": "CASA",
    "adv": "San Jose Earthquakes",
    "c_pro_ht": 5,
    "c_sof_ht": 2,
    "c_pro_2t": 5,
    "c_sof_2t": 1,
    "c_pro_ft": 10,
    "c_sof_ft": 3,
    "gols_pro_ht": 0,
    "gols_sof_ht": 1,
    "gols_pro_ft": 2,
    "gols_sof_ft": 3,
    "posse": 58,
    "fin": 21
   },
   {
    "data": "03.05.2026 18:30",
    "rodada": "R9",
    "local": "FORA",
    "adv": "Austin FC",
    "c_pro_ht": 4,
    "c_sof_ht": 2,
    "c_pro_2t": 2,
    "c_sof_2t": 2,
    "c_pro_ft": 6,
    "c_sof_ft": 4,
    "gols_pro_ht": 0,
    "gols_sof_ht": 0,
    "gols_pro_ft": 0,
    "gols_sof_ft": 2,
    "posse": 45,
    "fin": 15
   },
   {
    "data": "09.05.2026 22:30",
    "rodada": "R10",
    "local": "FORA",
    "adv": "Colorado Rapids",
    "c_pro_ht": 0,
    "c_sof_ht": 6,
    "c_pro_2t": 1,
    "c_sof_2t": 5,
    "c_pro_ft": 1,
    "c_sof_ft": 11,
    "gols_pro_ht": 1,
    "gols_sof_ht": 0,
    "gols_pro_ft": 1,
    "gols_sof_ft": 0,
    "posse": 44,
    "fin": 10
   },
   {
    "data": "13.05.2026 21:30",
    "rodada": "R11",
    "local": "CASA",
    "adv": "Los Angeles FC",
    "c_pro_ht": 2,
    "c_sof_ht": 2,
    "c_pro_2t": 0,
    "c_sof_2t": 6,
    "c_pro_ft": 2,
    "c_sof_ft": 8,
    "gols_pro_ht": 1,
    "gols_sof_ht": 0,
    "gols_pro_ft": 2,
    "gols_sof_ft": 1,
    "posse": 38,
    "fin": 8
   },
   {
    "data": "16.05.2026 20:30",
    "rodada": "R12",
    "local": "FORA",
    "adv": "DC United",
    "c_pro_ht": 8,
    "c_sof_ht": 3,
    "c_pro_2t": 0,
    "c_sof_2t": 2,
    "c_pro_ft": 8,
    "c_sof_ft": 5,
    "gols_pro_ht": 0,
    "gols_sof_ht": 0,
    "gols_pro_ft": 1,
    "gols_sof_ft": 1,
    "posse": 57,
    "fin": 16
   }
  ]
 },
 "Toronto FC": {
  "time": "Toronto FC",
  "n_jogos_total": 5,
  "n_casa": 4,
  "n_fora": 1,
  "volume": {
   "casa_pro_ft": 6.5,
   "casa_sof_ft": 6.25,
   "casa_total_ft": 12.75,
   "fora_pro_ft": 3,
   "fora_sof_ft": 7,
   "fora_total_ft": 10
  },
  "pos_gol_pro": null,
  "pos_gol_contra": {
   "n": 3,
   "c_2t_pro": 2.67,
   "c_2t_sof": 3,
   "diff": -0.33,
   "estilo": "EQUILIBRADO_REACAO"
  },
  "distribuicao_HT2T": {
   "pct_ht": 31.0,
   "categoria": "ASFIXIA_FINAL",
   "ht_pro_avg": 1.8,
   "t2_pro_avg": 4
  },
  "sangrador": {
   "sof_avg": 6.4,
   "posse_avg": 47.8,
   "tipo": "SANGRA_SEM_BOLA"
  },
  "eficacia": {
   "cantos_por_gol": 3.62,
   "categoria": "NORMAL",
   "total_gols": 8,
   "total_cantos": 29
  },
  "regime_atual": {
   "status": "⚪ NEUTRO",
   "obs": "Sem direção clara | sd 2.6 | desvio -0.0",
   "ultimos_jogos": [
    8,
    8,
    4,
    3
   ]
  },
  "historico": [
   {
    "data": "18.04.2026 14:00",
    "rodada": "R7",
    "local": "CASA",
    "adv": "Austin FC",
    "c_pro_ht": 2,
    "c_sof_ht": 4,
    "c_pro_2t": 4,
    "c_sof_2t": 1,
    "c_pro_ft": 6,
    "c_sof_ft": 5,
    "gols_pro_ht": 0,
    "gols_sof_ht": 1,
    "gols_pro_ft": 3,
    "gols_sof_ft": 3,
    "posse": 46,
    "fin": 18
   },
   {
    "data": "25.04.2026 14:00",
    "rodada": "R8",
    "local": "CASA",
    "adv": "Atlanta Utd",
    "c_pro_ht": 1,
    "c_sof_ht": 5,
    "c_pro_2t": 7,
    "c_sof_2t": 2,
    "c_pro_ft": 8,
    "c_sof_ft": 7,
    "gols_pro_ht": 0,
    "gols_sof_ht": 0,
    "gols_pro_ft": 1,
    "gols_sof_ft": 2,
    "posse": 51,
    "fin": 9
   },
   {
    "data": "02.05.2026 14:00",
    "rodada": "R9",
    "local": "CASA",
    "adv": "San Jose Earthquakes",
    "c_pro_ht": 3,
    "c_sof_ht": 3,
    "c_pro_2t": 5,
    "c_sof_2t": 6,
    "c_pro_ft": 8,
    "c_sof_ft": 9,
    "gols_pro_ht": 1,
    "gols_sof_ht": 1,
    "gols_pro_ft": 1,
    "gols_sof_ft": 1,
    "posse": 48,
    "fin": 11
   },
   {
    "data": "09.05.2026 14:00",
    "rodada": "R10",
    "local": "CASA",
    "adv": "Inter Miami",
    "c_pro_ht": 2,
    "c_sof_ht": 0,
    "c_pro_2t": 2,
    "c_sof_2t": 4,
    "c_pro_ft": 4,
    "c_sof_ft": 4,
    "gols_pro_ht": 0,
    "gols_sof_ht": 1,
    "gols_pro_ft": 2,
    "gols_sof_ft": 4,
    "posse": 40,
    "fin": 13
   },
   {
    "data": "16.05.2026 20:30",
    "rodada": "R12",
    "local": "FORA",
    "adv": "Charlotte",
    "c_pro_ht": 1,
    "c_sof_ht": 3,
    "c_pro_2t": 2,
    "c_sof_2t": 4,
    "c_pro_ft": 3,
    "c_sof_ft": 7,
    "gols_pro_ht": 1,
    "gols_sof_ht": 2,
    "gols_pro_ft": 1,
    "gols_sof_ft": 3,
    "posse": 54,
    "fin": 13
   }
  ]
 },
 "Vancouver Whitecaps": {
  "time": "Vancouver Whitecaps",
  "n_jogos_total": 6,
  "n_casa": 2,
  "n_fora": 4,
  "volume": {
   "casa_pro_ft": 7,
   "casa_sof_ft": 3,
   "casa_total_ft": 10,
   "fora_pro_ft": 3.75,
   "fora_sof_ft": 3.25,
   "fora_total_ft": 7.0
  },
  "pos_gol_pro": {
   "n": 3,
   "c_2t_pro": 2.67,
   "c_2t_sof": 3,
   "diff": -0.33,
   "estilo": "EQUILIBRADO_POS_GOL"
  },
  "pos_gol_contra": null,
  "distribuicao_HT2T": {
   "pct_ht": 62.1,
   "categoria": "BLITZ_INICIAL",
   "ht_pro_avg": 3,
   "t2_pro_avg": 1.83
  },
  "sangrador": {
   "sof_avg": 3.17,
   "posse_avg": 54.3,
   "tipo": "DEFESA_SOLIDA"
  },
  "eficacia": {
   "cantos_por_gol": 2.64,
   "categoria": "CLINICA",
   "total_gols": 11,
   "total_cantos": 29
  },
  "regime_atual": {
   "status": "🟡 EMERGENTE",
   "obs": "Tendência emergente em baixa | sd 1.7 | desvio -1.1",
   "ultimos_jogos": [
    2,
    4,
    6,
    3
   ]
  },
  "historico": [
   {
    "data": "17.04.2026 23:30",
    "rodada": "R7",
    "local": "CASA",
    "adv": "Sporting Kansas City",
    "c_pro_ht": 5,
    "c_sof_ht": 0,
    "c_pro_2t": 1,
    "c_sof_2t": 3,
    "c_pro_ft": 6,
    "c_sof_ft": 3,
    "gols_pro_ht": 3,
    "gols_sof_ht": 0,
    "gols_pro_ft": 3,
    "gols_sof_ft": 0,
    "posse": 50,
    "fin": 25
   },
   {
    "data": "25.04.2026 23:30",
    "rodada": "R8",
    "local": "CASA",
    "adv": "Colorado Rapids",
    "c_pro_ht": 5,
    "c_sof_ht": 1,
    "c_pro_2t": 3,
    "c_sof_2t": 2,
    "c_pro_ft": 8,
    "c_sof_ft": 3,
    "gols_pro_ht": 2,
    "gols_sof_ht": 1,
    "gols_pro_ft": 3,
    "gols_sof_ft": 1,
    "posse": 45,
    "fin": 20
   },
   {
    "data": "02.05.2026 23:30",
    "rodada": "R9",
    "local": "FORA",
    "adv": "Los Angeles Galaxy",
    "c_pro_ht": 2,
    "c_sof_ht": 0,
    "c_pro_2t": 0,
    "c_sof_2t": 1,
    "c_pro_ft": 2,
    "c_sof_ft": 1,
    "gols_pro_ht": 0,
    "gols_sof_ht": 0,
    "gols_pro_ft": 1,
    "gols_sof_ft": 1,
    "posse": 62,
    "fin": 19
   },
   {
    "data": "09.05.2026 23:30",
    "rodada": "R10",
    "local": "FORA",
    "adv": "San Jose Earthquakes",
    "c_pro_ht": 3,
    "c_sof_ht": 2,
    "c_pro_2t": 1,
    "c_sof_2t": 0,
    "c_pro_ft": 4,
    "c_sof_ft": 2,
    "gols_pro_ht": 0,
    "gols_sof_ht": 1,
    "gols_pro_ft": 1,
    "gols_sof_ft": 1,
    "posse": 71,
    "fin": 16
   },
   {
    "data": "13.05.2026 21:30",
    "rodada": "R11",
    "local": "FORA",
    "adv": "FC Dallas",
    "c_pro_ht": 2,
    "c_sof_ht": 2,
    "c_pro_2t": 4,
    "c_sof_2t": 4,
    "c_pro_ft": 6,
    "c_sof_ft": 6,
    "gols_pro_ht": 2,
    "gols_sof_ht": 1,
    "gols_pro_ft": 3,
    "gols_sof_ft": 2,
    "posse": 51,
    "fin": 16
   },
   {
    "data": "16.05.2026 21:30",
    "rodada": "R12",
    "local": "FORA",
    "adv": "Houston Dynamo",
    "c_pro_ht": 1,
    "c_sof_ht": 2,
    "c_pro_2t": 2,
    "c_sof_2t": 2,
    "c_pro_ft": 3,
    "c_sof_ft": 4,
    "gols_pro_ht": 0,
    "gols_sof_ht": 0,
    "gols_pro_ft": 0,
    "gols_sof_ft": 1,
    "posse": 47,
    "fin": 9
   }
  ]
 }
}