[
  {
    "url": "https://www.flashscore.com/match/EyIigZJF/#/match-summary",
    "match_id": "EyIigZJF",
    "data_partida": "11.04.2026 15:30",
    "liga": "Primera B Nacional (Argentina)",
    "codigo_liga": "ARG_B",
    "rodada": null,
    "mandante": "Almagro",
    "visitante": "Patronato",
    "placar": {
      "ht": "0 - 0",
      "ft": "0 - 1"
    },
    "estatisticas_ft": {
      "posse": {
        "m": 43,
        "v": 57
      },
      "finalizacoes": {
        "m": 3,
        "v": 5
      },
      "chutes_alvo": {
        "m": 1,
        "v": 4
      },
      "cantos": {
        "m": 5,
        "v": 6
      },
      "cartoes_amarelos": {
        "m": 3,
        "v": 6
      },
      "cartoes_vermelhos": {
        "m": 0,
        "v": 1
      }
    },
    "estatisticas_ht": {
      "posse": {
        "m": 41,
        "v": 59
      },
      "finalizacoes": {
        "m": 1,
        "v": 0
      },
      "chutes_alvo": {
        "m": 0,
        "v": 0
      },
      "cantos": {
        "m": 1,
        "v": 5
      },
      "cartoes_amarelos": {
        "m": 1,
        "v": 1
      }
    },
    "formacao": {
      "m": "4-5-1",
      "v": "5-3-2"
    },
    "mercado": {
      "oddM": "2.40",
      "oddEmpate": "2.70",
      "oddV": "3.40"
    },
    "meta": {
      "fonte": "flashscore",
      "versao_analista": "v4",
      "timestamp_extracao": "2026-05-20T05:15:08.708Z",
      "campos_disponiveis": 15,
      "campos_falhados": [
        "ataques_perigosos_ft",
        "faltas_ft",
        "impedimentos_ft",
        "cruzamentos_ft",
        "defesas_goleiro_ft",
        "tiros_de_meta_ft",
        "laterais_ft",
        "passes_ft",
        "ataques_perigosos_ht",
        "faltas_ht",
        "impedimentos_ht",
        "cruzamentos_ht",
        "cartoes_vermelhos_ht",
        "defesas_goleiro_ht",
        "tiros_de_meta_ht",
        "laterais_ht",
        "passes_ht"
      ],
      "metodo_extracao": {
        "ft": "DOM",
        "ht": "DOM"
      }
    }
  },
  {
    "url": "https://www.flashscore.com/match/2HWHtdzA/#/match-summary",
    "match_id": "2HWHtdzA",
    "data_partida": "12.04.2026 15:00",
    "liga": "Primera B Nacional (Argentina)",
    "codigo_liga": "ARG_B",
    "rodada": null,
    "mandante": "Chacarita Juniors",
    "visitante": "Gimnasia y Tiro",
    "placar": {
      "ht": "2 - 0",
      "ft": "2 - 0"
    },
    "estatisticas_ft": {
      "posse": {
        "m": 50,
        "v": 50
      },
      "finalizacoes": {
        "m": 10,
        "v": 5
      },
      "chutes_alvo": {
        "m": 6,
        "v": 2
      },
      "cantos": {
        "m": 1,
        "v": 2
      },
      "cartoes_amarelos": {
        "m": 3,
        "v": 4
      }
    },
    "estatisticas_ht": {
      "posse": {
        "m": 54,
        "v": 46
      },
      "finalizacoes": {
        "m": 8,
        "v": 4
      },
      "chutes_alvo": {
        "m": 5,
        "v": 2
      },
      "cantos": {
        "m": 1,
        "v": 1
      },
      "cartoes_amarelos": {
        "m": 1,
        "v": 0
      }
    },
    "formacao": {
      "m": "4-4-2",
      "v": "3-5-2"
    },
    "mercado": {
      "oddM": "2.15",
      "oddEmpate": "3.00",
      "oddV": "3.60"
    },
    "meta": {
      "fonte": "flashscore",
      "versao_analista": "v4",
      "timestamp_extracao": "2026-05-20T05:15:39.159Z",
      "campos_disponiveis": 14,
      "campos_falhados": [
        "ataques_perigosos_ft",
        "faltas_ft",
        "impedimentos_ft",
        "cruzamentos_ft",
        "cartoes_vermelhos_ft",
        "defesas_goleiro_ft",
        "tiros_de_meta_ft",
        "laterais_ft",
        "passes_ft",
        "ataques_perigosos_ht",
        "faltas_ht",
        "impedimentos_ht",
        "cruzamentos_ht",
        "cartoes_vermelhos_ht",
        "defesas_goleiro_ht",
        "tiros_de_meta_ht",
        "laterais_ht",
        "passes_ht"
      ],
      "metodo_extracao": {
        "ft": "DOM",
        "ht": "DOM"
      }
    }
  },
  {
    "url": "https://www.flashscore.com/match/nVHlzuem/#/match-summary",
    "match_id": "nVHlzuem",
    "data_partida": "27.02.2026 22:00",
    "liga": "Primera B Nacional (Argentina)",
    "codigo_liga": "ARG_B",
    "rodada": null,
    "mandante": "Gimnasia y Tiro",
    "visitante": "Almagro",
    "placar": {
      "ht": "1 - 0",
      "ft": "2 - 0"
    },
    "estatisticas_ft": {
      "posse": {
        "m": 57,
        "v": 43
      },
      "finalizacoes": {
        "m": 12,
        "v": 4
      },
      "chutes_alvo": {
        "m": 5,
        "v": 2
      },
      "cantos": {
        "m": 6,
        "v": 2
      },
      "cartoes_amarelos": {
        "m": 0,
        "v": 3
      }
    },
    "estatisticas_ht": {
      "posse": {
        "m": 60,
        "v": 40
      },
      "finalizacoes": {
        "m": 7,
        "v": 1
      },
      "chutes_alvo": {
        "m": 3,
        "v": 1
      },
      "cantos": {
        "m": 5,
        "v": 1
      }
    },
    "formacao": {
      "m": "4-1-4-1",
      "v": "4-4-2"
    },
    "mercado": {
      "oddM": "1.79",
      "oddEmpate": "2.75",
      "oddV": "6.25"
    },
    "meta": {
      "fonte": "flashscore",
      "versao_analista": "v4",
      "timestamp_extracao": "2026-05-20T05:16:07.893Z",
      "campos_disponiveis": 13,
      "campos_falhados": [
        "ataques_perigosos_ft",
        "faltas_ft",
        "impedimentos_ft",
        "cruzamentos_ft",
        "cartoes_vermelhos_ft",
        "defesas_goleiro_ft",
        "tiros_de_meta_ft",
        "laterais_ft",
        "passes_ft",
        "ataques_perigosos_ht",
        "faltas_ht",
        "impedimentos_ht",
        "cruzamentos_ht",
        "cartoes_amarelos_ht",
        "cartoes_vermelhos_ht",
        "defesas_goleiro_ht",
        "tiros_de_meta_ht",
        "laterais_ht",
        "passes_ht"
      ],
      "metodo_extracao": {
        "ft": "DOM",
        "ht": "DOM"
      }
    }
  },
  {
    "url": "https://www.flashscore.com/match/tUCzTNmK/#/match-summary",
    "match_id": "tUCzTNmK",
    "data_partida": "21.02.2026 20:00",
    "liga": "Primera B Nacional (Argentina)",
    "codigo_liga": "ARG_B",
    "rodada": null,
    "mandante": "Patronato",
    "visitante": "Gimnasia y Tiro",
    "placar": {
      "ht": "0 - 1",
      "ft": "1 - 2"
    },
    "estatisticas_ft": {
      "posse": {
        "m": 47,
        "v": 53
      },
      "finalizacoes": {
        "m": 9,
        "v": 10
      },
      "chutes_alvo": {
        "m": 4,
        "v": 6
      },
      "cantos": {
        "m": 7,
        "v": 3
      },
      "cartoes_amarelos": {
        "m": 2,
        "v": 3
      }
    },
    "estatisticas_ht": {
      "posse": {
        "m": 42,
        "v": 58
      },
      "finalizacoes": {
        "m": 4,
        "v": 5
      },
      "chutes_alvo": {
        "m": 1,
        "v": 2
      },
      "cantos": {
        "m": 3,
        "v": 2
      },
      "cartoes_amarelos": {
        "m": 1,
        "v": 1
      }
    },
    "formacao": {
      "m": "5-4-1",
      "v": "4-4-2"
    },
    "mercado": {
      "oddM": "2.40",
      "oddEmpate": "2.75",
      "oddV": "3.30"
    },
    "meta": {
      "fonte": "flashscore",
      "versao_analista": "v4",
      "timestamp_extracao": "2026-05-20T05:16:38.279Z",
      "campos_disponiveis": 14,
      "campos_falhados": [
        "ataques_perigosos_ft",
        "faltas_ft",
        "impedimentos_ft",
        "cruzamentos_ft",
        "cartoes_vermelhos_ft",
        "defesas_goleiro_ft",
        "tiros_de_meta_ft",
        "laterais_ft",
        "passes_ft",
        "ataques_perigosos_ht",
        "faltas_ht",
        "impedimentos_ht",
        "cruzamentos_ht",
        "cartoes_vermelhos_ht",
        "defesas_goleiro_ht",
        "tiros_de_meta_ht",
        "laterais_ht",
        "passes_ht"
      ],
      "metodo_extracao": {
        "ft": "DOM",
        "ht": "DOM"
      }
    }
  },
  {
    "url": "https://www.flashscore.com/match/0Iki0YDG/#/match-summary",
    "match_id": "0Iki0YDG",
    "data_partida": "13.02.2026 22:00",
    "liga": "Primera B Nacional (Argentina)",
    "codigo_liga": "ARG_B",
    "rodada": null,
    "mandante": "Gimnasia y Tiro",
    "visitante": "Colegiales",
    "placar": {
      "ht": "2 - 0",
      "ft": "2 - 1"
    },
    "estatisticas_ft": {
      "posse": {
        "m": 61,
        "v": 39
      },
      "finalizacoes": {
        "m": 7,
        "v": 6
      },
      "chutes_alvo": {
        "m": 5,
        "v": 5
      },
      "cantos": {
        "m": 6,
        "v": 4
      },
      "cartoes_amarelos": {
        "m": 3,
        "v": 2
      }
    },
    "estatisticas_ht": {
      "posse": {
        "m": 63,
        "v": 37
      },
      "finalizacoes": {
        "m": 5,
        "v": 1
      },
      "chutes_alvo": {
        "m": 4,
        "v": 1
      },
      "cantos": {
        "m": 3,
        "v": 3
      },
      "cartoes_amarelos": {
        "m": 2,
        "v": 1
      }
    },
    "formacao": {
      "m": "4-2-3-1",
      "v": "5-3-2"
    },
    "mercado": {
      "oddM": "1.71",
      "oddEmpate": "3.10",
      "oddV": "5.75"
    },
    "meta": {
      "fonte": "flashscore",
      "versao_analista": "v4",
      "timestamp_extracao": "2026-05-20T05:17:08.197Z",
      "campos_disponiveis": 14,
      "campos_falhados": [
        "ataques_perigosos_ft",
        "faltas_ft",
        "impedimentos_ft",
        "cruzamentos_ft",
        "cartoes_vermelhos_ft",
        "defesas_goleiro_ft",
        "tiros_de_meta_ft",
        "laterais_ft",
        "passes_ft",
        "ataques_perigosos_ht",
        "faltas_ht",
        "impedimentos_ht",
        "cruzamentos_ht",
        "cartoes_vermelhos_ht",
        "defesas_goleiro_ht",
        "tiros_de_meta_ht",
        "laterais_ht",
        "passes_ht"
      ],
      "metodo_extracao": {
        "ft": "DOM",
        "ht": "DOM"
      }
    }
  },
  {
    "url": "https://www.flashscore.com/match/Wb9EO2cR/#/match-summary",
    "match_id": "Wb9EO2cR",
    "data_partida": "22.03.2026 17:00",
    "liga": "Primera B Nacional (Argentina)",
    "codigo_liga": "ARG_B",
    "rodada": null,
    "mandante": "Club A. Guemes",
    "visitante": "Agropecuario",
    "placar": {
      "ht": "1 - 0",
      "ft": "1 - 1"
    },
    "estatisticas_ft": {
      "posse": {
        "m": 52,
        "v": 48
      },
      "finalizacoes": {
        "m": 7,
        "v": 14
      },
      "chutes_alvo": {
        "m": 3,
        "v": 5
      },
      "cantos": {
        "m": 1,
        "v": 3
      },
      "cartoes_amarelos": {
        "m": 3,
        "v": 1
      }
    },
    "estatisticas_ht": {
      "posse": {
        "m": 61,
        "v": 39
      },
      "finalizacoes": {
        "m": 4,
        "v": 7
      },
      "chutes_alvo": {
        "m": 3,
        "v": 2
      },
      "cantos": {
        "m": 0,
        "v": 1
      },
      "cartoes_amarelos": {
        "m": 2,
        "v": 0
      }
    },
    "formacao": {
      "m": "4-2-3-1",
      "v": "4-2-3-1"
    },
    "mercado": {
      "oddM": "2.25",
      "oddEmpate": "2.82",
      "oddV": "3.50"
    },
    "meta": {
      "fonte": "flashscore",
      "versao_analista": "v4",
      "timestamp_extracao": "2026-05-20T05:17:36.922Z",
      "campos_disponiveis": 14,
      "campos_falhados": [
        "ataques_perigosos_ft",
        "faltas_ft",
        "impedimentos_ft",
        "cruzamentos_ft",
        "cartoes_vermelhos_ft",
        "defesas_goleiro_ft",
        "tiros_de_meta_ft",
        "laterais_ft",
        "passes_ft",
        "ataques_perigosos_ht",
        "faltas_ht",
        "impedimentos_ht",
        "cruzamentos_ht",
        "cartoes_vermelhos_ht",
        "defesas_goleiro_ht",
        "tiros_de_meta_ht",
        "laterais_ht",
        "passes_ht"
      ],
      "metodo_extracao": {
        "ft": "DOM",
        "ht": "DOM"
      }
    }
  },
  {
    "url": "https://www.flashscore.com/match/KtoaTWs3/#/match-summary",
    "match_id": "KtoaTWs3",
    "data_partida": "21.02.2026 20:00",
    "liga": "Primera B Nacional (Argentina)",
    "codigo_liga": "ARG_B",
    "rodada": null,
    "mandante": "San Martin S.J.",
    "visitante": "Club A. Guemes",
    "placar": {
      "ht": "1 - 0",
      "ft": "2 - 1"
    },
    "estatisticas_ft": {
      "posse": {
        "m": 62,
        "v": 38
      },
      "finalizacoes": {
        "m": 11,
        "v": 10
      },
      "chutes_alvo": {
        "m": 5,
        "v": 6
      },
      "cantos": {
        "m": 14,
        "v": 6
      },
      "cartoes_amarelos": {
        "m": 0,
        "v": 2
      }
    },
    "estatisticas_ht": {
      "posse": {
        "m": 54,
        "v": 46
      },
      "finalizacoes": {
        "m": 5,
        "v": 4
      },
      "chutes_alvo": {
        "m": 2,
        "v": 2
      },
      "cantos": {
        "m": 7,
        "v": 2
      },
      "cartoes_amarelos": {
        "m": 0,
        "v": 1
      }
    },
    "formacao": {
      "m": "4-3-3",
      "v": "4-4-2"
    },
    "mercado": {
      "oddM": "1.91",
      "oddEmpate": "2.75",
      "oddV": "5.25"
    },
    "meta": {
      "fonte": "flashscore",
      "versao_analista": "v4",
      "timestamp_extracao": "2026-05-20T05:18:05.234Z",
      "campos_disponiveis": 14,
      "campos_falhados": [
        "ataques_perigosos_ft",
        "faltas_ft",
        "impedimentos_ft",
        "cruzamentos_ft",
        "cartoes_vermelhos_ft",
        "defesas_goleiro_ft",
        "tiros_de_meta_ft",
        "laterais_ft",
        "passes_ft",
        "ataques_perigosos_ht",
        "faltas_ht",
        "impedimentos_ht",
        "cruzamentos_ht",
        "cartoes_vermelhos_ht",
        "defesas_goleiro_ht",
        "tiros_de_meta_ht",
        "laterais_ht",
        "passes_ht"
      ],
      "metodo_extracao": {
        "ft": "DOM",
        "ht": "DOM"
      }
    }
  },
  {
    "url": "https://www.flashscore.com/match/lvzB4s6e/#/match-summary",
    "match_id": "lvzB4s6e",
    "data_partida": "15.03.2026 16:00",
    "liga": "Primera B Nacional (Argentina)",
    "codigo_liga": "ARG_B",
    "rodada": null,
    "mandante": "Agropecuario",
    "visitante": "Chacarita Juniors",
    "placar": {
      "ht": "1 - 0",
      "ft": "2 - 0"
    },
    "estatisticas_ft": {
      "posse": {
        "m": 45,
        "v": 55
      },
      "finalizacoes": {
        "m": 10,
        "v": 8
      },
      "chutes_alvo": {
        "m": 6,
        "v": 6
      },
      "cantos": {
        "m": 0,
        "v": 7
      },
      "cartoes_amarelos": {
        "m": 4,
        "v": 5
      }
    },
    "estatisticas_ht": {
      "posse": {
        "m": 44,
        "v": 56
      },
      "finalizacoes": {
        "m": 5,
        "v": 5
      },
      "chutes_alvo": {
        "m": 3,
        "v": 3
      },
      "cantos": {
        "m": 0,
        "v": 1
      },
      "cartoes_amarelos": {
        "m": 3,
        "v": 2
      }
    },
    "formacao": {
      "m": "4-3-3",
      "v": "4-3-3"
    },
    "mercado": {
      "oddM": "2.01",
      "oddEmpate": "3.00",
      "oddV": "4.10"
    },
    "meta": {
      "fonte": "flashscore",
      "versao_analista": "v4",
      "timestamp_extracao": "2026-05-20T05:18:34.461Z",
      "campos_disponiveis": 14,
      "campos_falhados": [
        "ataques_perigosos_ft",
        "faltas_ft",
        "impedimentos_ft",
        "cruzamentos_ft",
        "cartoes_vermelhos_ft",
        "defesas_goleiro_ft",
        "tiros_de_meta_ft",
        "laterais_ft",
        "passes_ft",
        "ataques_perigosos_ht",
        "faltas_ht",
        "impedimentos_ht",
        "cruzamentos_ht",
        "cartoes_vermelhos_ht",
        "defesas_goleiro_ht",
        "tiros_de_meta_ht",
        "laterais_ht",
        "passes_ht"
      ],
      "metodo_extracao": {
        "ft": "DOM",
        "ht": "DOM"
      }
    }
  },
  {
    "url": "https://www.flashscore.com/match/nwj57kLq/#/match-summary",
    "match_id": "nwj57kLq",
    "data_partida": "15.02.2026 17:00",
    "liga": "Primera B Nacional (Argentina)",
    "codigo_liga": "ARG_B",
    "rodada": null,
    "mandante": "Chacarita Juniors",
    "visitante": "San Martin S.J.",
    "placar": {
      "ht": "1 - 1",
      "ft": "1 - 1"
    },
    "estatisticas_ft": {
      "posse": {
        "m": 55,
        "v": 45
      },
      "finalizacoes": {
        "m": 10,
        "v": 5
      },
      "chutes_alvo": {
        "m": 4,
        "v": 2
      },
      "cantos": {
        "m": 7,
        "v": 3
      },
      "cartoes_amarelos": {
        "m": 3,
        "v": 2
      }
    },
    "estatisticas_ht": {
      "posse": {
        "m": 58,
        "v": 42
      },
      "finalizacoes": {
        "m": 6,
        "v": 4
      },
      "chutes_alvo": {
        "m": 3,
        "v": 2
      },
      "cantos": {
        "m": 4,
        "v": 2
      },
      "cartoes_amarelos": {
        "m": 1,
        "v": 0
      }
    },
    "formacao": {
      "m": "4-4-2",
      "v": "4-2-3-1"
    },
    "mercado": {
      "oddM": "2.40",
      "oddEmpate": "2.57",
      "oddV": "3.50"
    },
    "meta": {
      "fonte": "flashscore",
      "versao_analista": "v4",
      "timestamp_extracao": "2026-05-20T05:19:03.602Z",
      "campos_disponiveis": 14,
      "campos_falhados": [
        "ataques_perigosos_ft",
        "faltas_ft",
        "impedimentos_ft",
        "cruzamentos_ft",
        "cartoes_vermelhos_ft",
        "defesas_goleiro_ft",
        "tiros_de_meta_ft",
        "laterais_ft",
        "passes_ft",
        "ataques_perigosos_ht",
        "faltas_ht",
        "impedimentos_ht",
        "cruzamentos_ht",
        "cartoes_vermelhos_ht",
        "defesas_goleiro_ht",
        "tiros_de_meta_ht",
        "laterais_ht",
        "passes_ht"
      ],
      "metodo_extracao": {
        "ft": "DOM",
        "ht": "DOM"
      }
    }
  },
  {
    "url": "https://www.flashscore.com/match/bDHHGgbc/#/match-summary",
    "match_id": "bDHHGgbc",
    "data_partida": "14.02.2026 18:00",
    "liga": "Primera B Nacional (Argentina)",
    "codigo_liga": "ARG_B",
    "rodada": null,
    "mandante": "Agropecuario",
    "visitante": "Deportivo Maipu",
    "placar": {
      "ht": "0 - 1",
      "ft": "2 - 1"
    },
    "estatisticas_ft": {
      "posse": {
        "m": 46,
        "v": 54
      },
      "finalizacoes": {
        "m": 10,
        "v": 5
      },
      "chutes_alvo": {
        "m": 7,
        "v": 4
      },
      "cantos": {
        "m": 7,
        "v": 4
      },
      "cartoes_amarelos": {
        "m": 1,
        "v": 2
      }
    },
    "estatisticas_ht": {
      "posse": {
        "m": 51,
        "v": 49
      },
      "finalizacoes": {
        "m": 2,
        "v": 4
      },
      "chutes_alvo": {
        "m": 1,
        "v": 3
      },
      "cantos": {
        "m": 2,
        "v": 1
      },
      "cartoes_amarelos": {
        "m": 1,
        "v": 1
      }
    },
    "formacao": {
      "m": "5-3-2",
      "v": "4-4-2"
    },
    "mercado": {
      "oddM": "1.96",
      "oddEmpate": "3.00",
      "oddV": "4.10"
    },
    "meta": {
      "fonte": "flashscore",
      "versao_analista": "v4",
      "timestamp_extracao": "2026-05-20T05:19:34.295Z",
      "campos_disponiveis": 14,
      "campos_falhados": [
        "ataques_perigosos_ft",
        "faltas_ft",
        "impedimentos_ft",
        "cruzamentos_ft",
        "cartoes_vermelhos_ft",
        "defesas_goleiro_ft",
        "tiros_de_meta_ft",
        "laterais_ft",
        "passes_ft",
        "ataques_perigosos_ht",
        "faltas_ht",
        "impedimentos_ht",
        "cruzamentos_ht",
        "cartoes_vermelhos_ht",
        "defesas_goleiro_ht",
        "tiros_de_meta_ht",
        "laterais_ht",
        "passes_ht"
      ],
      "metodo_extracao": {
        "ft": "DOM",
        "ht": "DOM"
      }
    }
  },
  {
    "url": "https://www.flashscore.com/match/b7tQD606/#/match-summary",
    "match_id": "b7tQD606",
    "data_partida": "22.03.2026 16:00",
    "liga": "Primera B Nacional (Argentina)",
    "codigo_liga": "ARG_B",
    "rodada": null,
    "mandante": "Patronato",
    "visitante": "Colegiales",
    "placar": {
      "ht": "1 - 0",
      "ft": "2 - 0"
    },
    "estatisticas_ft": {
      "posse": {
        "m": 56,
        "v": 44
      },
      "finalizacoes": {
        "m": 14,
        "v": 15
      },
      "chutes_alvo": {
        "m": 7,
        "v": 7
      },
      "cantos": {
        "m": 3,
        "v": 8
      },
      "cartoes_amarelos": {
        "m": 1,
        "v": 2
      }
    },
    "estatisticas_ht": {
      "posse": {
        "m": 51,
        "v": 49
      },
      "finalizacoes": {
        "m": 6,
        "v": 2
      },
      "chutes_alvo": {
        "m": 3,
        "v": 1
      },
      "cantos": {
        "m": 2,
        "v": 3
      },
      "cartoes_amarelos": {
        "m": 1,
        "v": 1
      }
    },
    "formacao": {
      "m": "4-2-3-1",
      "v": "4-2-3-1"
    },
    "mercado": {
      "oddM": "1.86",
      "oddEmpate": "2.85",
      "oddV": "5.00"
    },
    "meta": {
      "fonte": "flashscore",
      "versao_analista": "v4",
      "timestamp_extracao": "2026-05-20T05:20:04.914Z",
      "campos_disponiveis": 14,
      "campos_falhados": [
        "ataques_perigosos_ft",
        "faltas_ft",
        "impedimentos_ft",
        "cruzamentos_ft",
        "cartoes_vermelhos_ft",
        "defesas_goleiro_ft",
        "tiros_de_meta_ft",
        "laterais_ft",
        "passes_ft",
        "ataques_perigosos_ht",
        "faltas_ht",
        "impedimentos_ht",
        "cruzamentos_ht",
        "cartoes_vermelhos_ht",
        "defesas_goleiro_ht",
        "tiros_de_meta_ht",
        "laterais_ht",
        "passes_ht"
      ],
      "metodo_extracao": {
        "ft": "DOM",
        "ht": "DOM"
      }
    }
  },
  {
    "url": "https://www.flashscore.com/match/GnRIu1XP/#/match-summary",
    "match_id": "GnRIu1XP",
    "data_partida": "02.03.2026 21:00",
    "liga": "Primera B Nacional (Argentina)",
    "codigo_liga": "ARG_B",
    "rodada": null,
    "mandante": "Atletico Atlanta",
    "visitante": "Patronato",
    "placar": {
      "ht": "0 - 0",
      "ft": "0 - 0"
    },
    "estatisticas_ft": {
      "posse": {
        "m": 58,
        "v": 42
      },
      "finalizacoes": {
        "m": 5,
        "v": 8
      },
      "chutes_alvo": {
        "m": 1,
        "v": 2
      },
      "cantos": {
        "m": 6,
        "v": 5
      },
      "cartoes_amarelos": {
        "m": 2,
        "v": 5
      }
    },
    "estatisticas_ht": {
      "posse": {
        "m": 63,
        "v": 37
      },
      "finalizacoes": {
        "m": 1,
        "v": 4
      },
      "chutes_alvo": {
        "m": 0,
        "v": 0
      },
      "cantos": {
        "m": 1,
        "v": 4
      },
      "cartoes_amarelos": {
        "m": 0,
        "v": 2
      }
    },
    "formacao": {
      "m": "4-4-2",
      "v": "4-4-2"
    },
    "mercado": {
      "oddM": "1.68",
      "oddEmpate": "3.30",
      "oddV": "5.25"
    },
    "meta": {
      "fonte": "flashscore",
      "versao_analista": "v4",
      "timestamp_extracao": "2026-05-20T05:20:34.733Z",
      "campos_disponiveis": 14,
      "campos_falhados": [
        "ataques_perigosos_ft",
        "faltas_ft",
        "impedimentos_ft",
        "cruzamentos_ft",
        "cartoes_vermelhos_ft",
        "defesas_goleiro_ft",
        "tiros_de_meta_ft",
        "laterais_ft",
        "passes_ft",
        "ataques_perigosos_ht",
        "faltas_ht",
        "impedimentos_ht",
        "cruzamentos_ht",
        "cartoes_vermelhos_ht",
        "defesas_goleiro_ht",
        "tiros_de_meta_ht",
        "laterais_ht",
        "passes_ht"
      ],
      "metodo_extracao": {
        "ft": "DOM",
        "ht": "DOM"
      }
    }
  },
  {
    "url": "https://www.flashscore.com/match/UTJyjri2/#/match-summary",
    "match_id": "UTJyjri2",
    "data_partida": "16.03.2026 21:00",
    "liga": "Primera B Nacional (Argentina)",
    "codigo_liga": "ARG_B",
    "rodada": null,
    "mandante": "Atletico Atlanta",
    "visitante": "Deportivo Maipu",
    "placar": {
      "ht": "1 - 0",
      "ft": "3 - 1"
    },
    "estatisticas_ft": {
      "posse": {
        "m": 54,
        "v": 46
      },
      "finalizacoes": {
        "m": 11,
        "v": 6
      },
      "chutes_alvo": {
        "m": 8,
        "v": 4
      },
      "cantos": {
        "m": 6,
        "v": 4
      },
      "cartoes_amarelos": {
        "m": 2,
        "v": 4
      }
    },
    "estatisticas_ht": {
      "posse": {
        "m": 53,
        "v": 47
      },
      "finalizacoes": {
        "m": 6,
        "v": 3
      },
      "chutes_alvo": {
        "m": 4,
        "v": 2
      },
      "cantos": {
        "m": 4,
        "v": 1
      }
    },
    "formacao": {
      "m": "4-4-2",
      "v": "4-4-2"
    },
    "mercado": {
      "oddM": "2.01",
      "oddEmpate": "2.70",
      "oddV": "4.50"
    },
    "meta": {
      "fonte": "flashscore",
      "versao_analista": "v4",
      "timestamp_extracao": "2026-05-20T05:21:04.895Z",
      "campos_disponiveis": 13,
      "campos_falhados": [
        "ataques_perigosos_ft",
        "faltas_ft",
        "impedimentos_ft",
        "cruzamentos_ft",
        "cartoes_vermelhos_ft",
        "defesas_goleiro_ft",
        "tiros_de_meta_ft",
        "laterais_ft",
        "passes_ft",
        "ataques_perigosos_ht",
        "faltas_ht",
        "impedimentos_ht",
        "cruzamentos_ht",
        "cartoes_amarelos_ht",
        "cartoes_vermelhos_ht",
        "defesas_goleiro_ht",
        "tiros_de_meta_ht",
        "laterais_ht",
        "passes_ht"
      ],
      "metodo_extracao": {
        "ft": "DOM",
        "ht": "DOM"
      }
    }
  },
  {
    "url": "https://www.flashscore.com/match/Q1l7N1Bs/#/match-summary",
    "match_id": "Q1l7N1Bs",
    "data_partida": "22.02.2026 20:00",
    "liga": "Primera B Nacional (Argentina)",
    "codigo_liga": "ARG_B",
    "rodada": null,
    "mandante": "Colegiales",
    "visitante": "Atletico Atlanta",
    "placar": {
      "ht": "0 - 0",
      "ft": "1 - 0"
    },
    "estatisticas_ft": {
      "posse": {
        "m": 38,
        "v": 62
      },
      "finalizacoes": {
        "m": 8,
        "v": 7
      },
      "chutes_alvo": {
        "m": 3,
        "v": 4
      },
      "cantos": {
        "m": 4,
        "v": 6
      },
      "cartoes_amarelos": {
        "m": 4,
        "v": 2
      }
    },
    "estatisticas_ht": {
      "posse": {
        "m": 30,
        "v": 70
      },
      "finalizacoes": {
        "m": 3,
        "v": 2
      },
      "chutes_alvo": {
        "m": 1,
        "v": 1
      },
      "cantos": {
        "m": 3,
        "v": 5
      },
      "cartoes_amarelos": {
        "m": 1,
        "v": 1
      }
    },
    "formacao": {
      "m": "4-4-2",
      "v": "4-3-3"
    },
    "mercado": {
      "oddM": "3.40",
      "oddEmpate": "2.65",
      "oddV": "2.50"
    },
    "meta": {
      "fonte": "flashscore",
      "versao_analista": "v4",
      "timestamp_extracao": "2026-05-20T05:21:34.716Z",
      "campos_disponiveis": 14,
      "campos_falhados": [
        "ataques_perigosos_ft",
        "faltas_ft",
        "impedimentos_ft",
        "cruzamentos_ft",
        "cartoes_vermelhos_ft",
        "defesas_goleiro_ft",
        "tiros_de_meta_ft",
        "laterais_ft",
        "passes_ft",
        "ataques_perigosos_ht",
        "faltas_ht",
        "impedimentos_ht",
        "cruzamentos_ht",
        "cartoes_vermelhos_ht",
        "defesas_goleiro_ht",
        "tiros_de_meta_ht",
        "laterais_ht",
        "passes_ht"
      ],
      "metodo_extracao": {
        "ft": "DOM",
        "ht": "DOM"
      }
    }
  },
  {
    "url": "https://www.flashscore.com/match/6BEqeek3/#/match-summary",
    "match_id": "6BEqeek3",
    "data_partida": "12.04.2026 18:30",
    "liga": "Primera B Nacional (Argentina)",
    "codigo_liga": "ARG_B",
    "rodada": null,
    "mandante": "Deportivo Maipu",
    "visitante": "Colegiales",
    "placar": {
      "ht": "1 - 0",
      "ft": "3 - 1"
    },
    "estatisticas_ft": {
      "posse": {
        "m": 49,
        "v": 51
      },
      "finalizacoes": {
        "m": 10,
        "v": 7
      },
      "chutes_alvo": {
        "m": 7,
        "v": 5
      },
      "cantos": {
        "m": 3,
        "v": 3
      },
      "cartoes_amarelos": {
        "m": 2,
        "v": 2
      }
    },
    "estatisticas_ht": {
      "posse": {
        "m": 51,
        "v": 49
      },
      "finalizacoes": {
        "m": 5,
        "v": 4
      },
      "chutes_alvo": {
        "m": 3,
        "v": 3
      },
      "cantos": {
        "m": 1,
        "v": 1
      }
    },
    "formacao": {
      "m": "4-4-2",
      "v": "4-4-2"
    },
    "mercado": {
      "oddM": "1.86",
      "oddEmpate": "2.85",
      "oddV": "4.75"
    },
    "meta": {
      "fonte": "flashscore",
      "versao_analista": "v4",
      "timestamp_extracao": "2026-05-20T05:22:03.557Z",
      "campos_disponiveis": 13,
      "campos_falhados": [
        "ataques_perigosos_ft",
        "faltas_ft",
        "impedimentos_ft",
        "cruzamentos_ft",
        "cartoes_vermelhos_ft",
        "defesas_goleiro_ft",
        "tiros_de_meta_ft",
        "laterais_ft",
        "passes_ft",
        "ataques_perigosos_ht",
        "faltas_ht",
        "impedimentos_ht",
        "cruzamentos_ht",
        "cartoes_amarelos_ht",
        "cartoes_vermelhos_ht",
        "defesas_goleiro_ht",
        "tiros_de_meta_ht",
        "laterais_ht",
        "passes_ht"
      ],
      "metodo_extracao": {
        "ft": "DOM",
        "ht": "DOM"
      }
    }
  },
  {
    "url": "https://www.flashscore.com/match/IkYlZDSq/#/match-summary",
    "match_id": "IkYlZDSq",
    "data_partida": "13.04.2026 19:00",
    "liga": "Primera B Nacional (Argentina)",
    "codigo_liga": "ARG_B",
    "rodada": null,
    "mandante": "Nueva Chicago",
    "visitante": "Midland",
    "placar": {
      "ht": "0 - 1",
      "ft": "2 - 2"
    },
    "estatisticas_ft": {
      "posse": {
        "m": 49,
        "v": 51
      },
      "finalizacoes": {
        "m": 8,
        "v": 17
      },
      "chutes_alvo": {
        "m": 6,
        "v": 8
      },
      "cantos": {
        "m": 1,
        "v": 6
      },
      "cartoes_amarelos": {
        "m": 4,
        "v": 6
      }
    },
    "estatisticas_ht": {
      "posse": {
        "m": 45,
        "v": 55
      },
      "finalizacoes": {
        "m": 0,
        "v": 10
      },
      "chutes_alvo": {
        "m": 0,
        "v": 5
      },
      "cantos": {
        "m": 1,
        "v": 4
      },
      "cartoes_amarelos": {
        "m": 0,
        "v": 1
      }
    },
    "formacao": {
      "m": "4-4-2",
      "v": "4-4-2"
    },
    "mercado": {
      "oddM": "3.10",
      "oddEmpate": "2.45",
      "oddV": "2.85"
    },
    "meta": {
      "fonte": "flashscore",
      "versao_analista": "v4",
      "timestamp_extracao": "2026-05-20T05:22:32.652Z",
      "campos_disponiveis": 14,
      "campos_falhados": [
        "ataques_perigosos_ft",
        "faltas_ft",
        "impedimentos_ft",
        "cruzamentos_ft",
        "cartoes_vermelhos_ft",
        "defesas_goleiro_ft",
        "tiros_de_meta_ft",
        "laterais_ft",
        "passes_ft",
        "ataques_perigosos_ht",
        "faltas_ht",
        "impedimentos_ht",
        "cruzamentos_ht",
        "cartoes_vermelhos_ht",
        "defesas_goleiro_ht",
        "tiros_de_meta_ht",
        "laterais_ht",
        "passes_ht"
      ],
      "metodo_extracao": {
        "ft": "DOM",
        "ht": "DOM"
      }
    }
  }
]